Workbook

Sheet Synthèse
A1: LIMA → RIO DE JANEIRO — 17 jours, 100 % en bus
A2: Pérou · Bolivie · Paraguay · Brésil — 5 200 km de route, 5 nuits en bus, 12 nuits en auberge
A3: Une feuille par jour (J01 à J17). Coûts en monnaie locale et en dollars US, moyen de paiement indiqué ligne par ligne.
A5: Jour | B5: Étape | C5: Programme | D5: Nuit | E5: Budget USD min | F5: Budget USD max
A6: J1 | B6: LIMA (Pérou) | C6: Lima — centre historique puis bus de nuit vers Puno | D6: Bus (Lima → Puno) | E6: ='J01 - Lima'!G18 | F6: ='J01 - Lima'!H18
A7: J2 | B7: PUNO (Pérou) | C7: Arrivée sur le lac Titicaca — acclimatation | D7: Hostal Puno | E7: ='J02 - Puno'!G19 | F7: ='J02 - Puno'!H19
A8: J3 | B8: PUNO → COPACABANA (Bolivie) | C8: Passage de frontière à Kasani — côté bolivien du Titicaca | D8: Hostal Copacabana | E8: ='J03 - Puno-Copacabana'!G23 | F8: ='J03 - Puno-Copacabana'!H23
A9: J4 | B9: ISLA DEL SOL (Bolivie) | C9: Journée complète sur l'île du Soleil — berceau inca | D9: Hostal Copacabana | E9: ='J04 - Isla del Sol'!G19 | F9: ='J04 - Isla del Sol'!H19
A10: J5 | B10: COPACABANA → LA PAZ | C10: Détroit de Tiquina et descente sur La Paz | D10: Hostel La Paz | E10: ='J05 - Copacabana-La Paz'!G18 | F10: ='J05 - Copacabana-La Paz'!H18
A11: J6 | B11: LA PAZ — jour 1 | C11: Téléphériques, El Alto, marchés et miradors | D11: Hostel La Paz | E11: ='J06 - La Paz 1'!G20 | F11: ='J06 - La Paz 1'!H20
A12: J7 | B12: LA PAZ — jour 2 | C12: Route de la Mort à VTT, puis bus de nuit vers Santa Cruz | D12: Bus (La Paz → Santa Cruz) | E12: ='J07 - La Paz 2'!G17 | F12: ='J07 - La Paz 2'!H17
A13: J8 | B13: SANTA CRUZ (transit) | C13: Escale de 6 h puis départ pour le Chaco | D13: Bus (Santa Cruz → Asunción) | E13: ='J08 - Santa Cruz'!G18 | F13: ='J08 - Santa Cruz'!H18
A14: J9 | B14: CHACO → ASUNCIÓN (Paraguay) | C14: Traversée du Chaco et double frontière | D14: Hostel Asunción | E14: ='J09 - Chaco-Asuncion'!G17 | F14: ='J09 - Chaco-Asuncion'!H17
A15: J10 | B15: ASUNCIÓN — jour 1 | C15: Centre historique, Mercado 4 et Costanera | D15: Hostel Asunción | E15: ='J10 - Asuncion 1'!G20 | F15: ='J10 - Asuncion 1'!H20
A16: J11 | B16: ASUNCIÓN — jour 2 | C16: Lac Ypacaraí (Areguá) et préparation du grand bus | D16: Hostel Asunción | E16: ='J11 - Asuncion 2'!G17 | F16: ='J11 - Asuncion 2'!H17
A17: J12 | B17: ASUNCIÓN → SÃO PAULO | C17: 21 h 30 de bus et passage au Brésil par le Pont de l'Amitié | D17: Bus (Asunción → São Paulo) | E17: ='J12 - Asuncion-Sao Paulo'!G16 | F17: ='J12 - Asuncion-Sao Paulo'!H16
A18: J13 | B18: SÃO PAULO — jour 1 | C18: Arrivée à l'aube, Avenida Paulista et centre | D18: Auberge São Paulo | E18: ='J13 - Sao Paulo 1'!G19 | F18: ='J13 - Sao Paulo 1'!H19
A19: J14 | B19: SÃO PAULO — jour 2 | C19: Luz, Mercadão, Ibirapuera, Liberdade — puis bus de nuit | D19: Bus (São Paulo → Rio) | E19: ='J14 - Sao Paulo 2'!G19 | F19: ='J14 - Sao Paulo 2'!H19
A20: J15 | B20: RIO DE JANEIRO — jour 1 | C20: CHRIST RÉDEMPTEUR, Santa Teresa et Lapa | D20: Auberge Rio | E20: ='J15 - Rio 1'!G18 | F20: ='J15 - Rio 1'!H18
A21: J16 | B21: RIO DE JANEIRO — jour 2 | C21: Pain de Sucre, Copacabana et Ipanema | D21: Auberge Rio | E21: ='J16 - Rio 2'!G17 | F21: ='J16 - Rio 2'!H17
A22: J17 | B22: RIO DE JANEIRO — jour 3 | C22: Jardin botanique, Parque Lage, Maracanã et Porto Maravilha | D22: Auberge Rio | E22: ='J17 - Rio 3'!G16 | F22: ='J17 - Rio 3'!H16
A24: TOTAL SUR PLACE (J1 → J17) | E24: =SUM(E6:E22) | F24: =SUM(F6:F22)
A26: Sous-totaux par pays (USD)
B27: Pérou | C27: J1 – J3 | E27: =SUMIF('J01 - Lima'!$D$6:$D$16,"PEN",'J01 - Lima'!G6:G16)+SUMIF('J02 - Puno'!$D$6:$D$17,"PEN",'J02 - Puno'!G6:G17)+SUMIF('J03 - Puno-Copacabana'!$D$6:$D$21,"PEN",'J03 - Puno-Copacabana'!G6:G21) | F27: =SUMIF('J01 - Lima'!$D$6:$D$16,"PEN",'J01 - Lima'!H6:H16)+SUMIF('J02 - Puno'!$D$6:$D$17,"PEN",'J02 - Puno'!H6:H17)+SUMIF('J03 - Puno-Copacabana'!$D$6:$D$21,"PEN",'J03 - Puno-Copacabana'!H6:H21)
B28: Bolivie | C28: J3 – J9 | E28: =SUMIF('J03 - Puno-Copacabana'!$D$6:$D$21,"BOB",'J03 - Puno-Copacabana'!G6:G21)+SUMIF('J04 - Isla del Sol'!$D$6:$D$17,"BOB",'J04 - Isla del Sol'!G6:G17)+SUMIF('J05 - Copacabana-La Paz'!$D$6:$D$16,"BOB",'J05 - Copacabana-La Paz'!G6:G16)+SUMIF('J06 - La Paz 1'!$D$6:$D$18,"BOB",'J06 - La Paz 1'!G6:G18)+SUMIF('J07 - La Paz 2'!$D$6:$D$15,"BOB",'J07 - La Paz 2'!G6:G15)+SUMIF('J08 - Santa Cruz'!$D$6:$D$16,"BOB",'J08 - Santa Cruz'!G6:G16)+SUMIF('J09 - Chaco-Asuncion'!$D$6:$D$15,"BOB",'J09 - Chaco-Asuncion'!G6:G15) | F28: =SUMIF('J03 - Puno-Copacabana'!$D$6:$D$21,"BOB",'J03 - Puno-Copacabana'!H6:H21)+SUMIF('J04 - Isla del Sol'!$D$6:$D$17,"BOB",'J04 - Isla del Sol'!H6:H17)+SUMIF('J05 - Copacabana-La Paz'!$D$6:$D$16,"BOB",'J05 - Copacabana-La Paz'!H6:H16)+SUMIF('J06 - La Paz 1'!$D$6:$D$18,"BOB",'J06 - La Paz 1'!H6:H18)+SUMIF('J07 - La Paz 2'!$D$6:$D$15,"BOB",'J07 - La Paz 2'!H6:H15)+SUMIF('J08 - Santa Cruz'!$D$6:$D$16,"BOB",'J08 - Santa Cruz'!H6:H16)+SUMIF('J09 - Chaco-Asuncion'!$D$6:$D$15,"BOB",'J09 - Chaco-Asuncion'!H6:H15)
B29: Paraguay | C29: J9 – J12 | E29: =SUMIF('J09 - Chaco-Asuncion'!$D$6:$D$15,"PYG",'J09 - Chaco-Asuncion'!G6:G15)+SUMIF('J10 - Asuncion 1'!$D$6:$D$18,"PYG",'J10 - Asuncion 1'!G6:G18)+SUMIF('J11 - Asuncion 2'!$D$6:$D$15,"PYG",'J11 - Asuncion 2'!G6:G15)+SUMIF('J12 - Asuncion-Sao Paulo'!$D$6:$D$14,"PYG",'J12 - Asuncion-Sao Paulo'!G6:G14) | F29: =SUMIF('J09 - Chaco-Asuncion'!$D$6:$D$15,"PYG",'J09 - Chaco-Asuncion'!H6:H15)+SUMIF('J10 - Asuncion 1'!$D$6:$D$18,"PYG",'J10 - Asuncion 1'!H6:H18)+SUMIF('J11 - Asuncion 2'!$D$6:$D$15,"PYG",'J11 - Asuncion 2'!H6:H15)+SUMIF('J12 - Asuncion-Sao Paulo'!$D$6:$D$14,"PYG",'J12 - Asuncion-Sao Paulo'!H6:H14)
B30: Brésil | C30: J12 – J17 | E30: =SUMIF('J12 - Asuncion-Sao Paulo'!$D$6:$D$14,"BRL",'J12 - Asuncion-Sao Paulo'!G6:G14)+SUMIF('J13 - Sao Paulo 1'!$D$6:$D$17,"BRL",'J13 - Sao Paulo 1'!G6:G17)+SUMIF('J14 - Sao Paulo 2'!$D$6:$D$17,"BRL",'J14 - Sao Paulo 2'!G6:G17)+SUMIF('J15 - Rio 1'!$D$6:$D$16,"BRL",'J15 - Rio 1'!G6:G16)+SUMIF('J16 - Rio 2'!$D$6:$D$15,"BRL",'J16 - Rio 2'!G6:G15)+SUMIF('J17 - Rio 3'!$D$6:$D$14,"BRL",'J17 - Rio 3'!G6:G14) | F30: =SUMIF('J12 - Asuncion-Sao Paulo'!$D$6:$D$14,"BRL",'J12 - Asuncion-Sao Paulo'!H6:H14)+SUMIF('J13 - Sao Paulo 1'!$D$6:$D$17,"BRL",'J13 - Sao Paulo 1'!H6:H17)+SUMIF('J14 - Sao Paulo 2'!$D$6:$D$17,"BRL",'J14 - Sao Paulo 2'!H6:H17)+SUMIF('J15 - Rio 1'!$D$6:$D$16,"BRL",'J15 - Rio 1'!H6:H16)+SUMIF('J16 - Rio 2'!$D$6:$D$15,"BRL",'J16 - Rio 2'!H6:H15)+SUMIF('J17 - Rio 3'!$D$6:$D$14,"BRL",'J17 - Rio 3'!H6:H14)
A32: Fourchette basse : dortoir, repas de marché, bus publics, alternative économique à la Route de la Mort. Fourchette haute : chambres privées, restaurants, bus touristiques, Route de la Mort en VTT. Hors planning (vaccin, assurance, frais bancaires, réserve) : voir la feuille « Hors planning ».

Sheet Taux de change
A1: Taux de change — cellules d'entrée
A2: Relevés le 11/09/2026. Modifiez la colonne B : tout le classeur se recalcule.
A4: Devise | B4: Unités pour 1 USD | C4: Pays | D4: Remarque
A5: PEN | B5: 3.363 | C5: Pérou (sol, S/) | D5: Taux de marché. Retrait au DAB : S/ 18–25 de frais locaux en plus.
A6: BOB | B6: 12.04 | C6: Bolivie (boliviano, Bs) | D6: Taux officiel BCB. Marché parallèle ≈ Bs 11,75 : l'écart s'est refermé depuis la dévaluation de décembre 2025.
A7: PYG | B7: 5921.57 | C7: Paraguay (guaraní, Gs) | D7: Monnaie inéchangeable hors du Paraguay : ne gardez rien en sortant.
A8: BRL | B8: 5.115 | C8: Brésil (real, R$) | D8: Une carte type Revolut/Wise donne un meilleur taux que toutes les casas de câmbio.
A11: Légende : le bleu signale une valeur saisie à la main (donc modifiable). Tout le reste du classeur est calculé par formule.

Sheet Bus longue distance
A1: Les 7 trajets en bus
A2: Colonne vertébrale du voyage : 5 200 km, dont 5 nuits passées à bord.
A5: Jour | B5: Trajet | C5: Compagnies | D5: Distance | E5: Durée | F5: Devise | G5: Prix local min | H5: Prix local max | I5: Prix USD min | J5: Prix USD max
A6: J1 | B6: Lima → Puno | C6: Civa Excluciva, Cruz del Sur Suite | D6: 1 300 km | E6: 21 h – 22 h | F6: PEN | G6: 150 | H6: 230 | I6: =G6/INDEX('Taux de change'!$B$5:$B$8,MATCH($F6,'Taux de change'!$A$5:$A$8,0)) | J6: =H6/INDEX('Taux de change'!$B$5:$B$8,MATCH($F6,'Taux de change'!$A$5:$A$8,0))
A7: J3 | B7: Puno → Copacabana | C7: Trans Titicaca, Tour Perú, Trans Zela | D7: 150 km | E7: 3 h 30 – 4 h (frontière incluse) | F7: PEN | G7: 30 | H7: 45 | I7: =G7/INDEX('Taux de change'!$B$5:$B$8,MATCH($F7,'Taux de change'!$A$5:$A$8,0)) | J7: =H7/INDEX('Taux de change'!$B$5:$B$8,MATCH($F7,'Taux de change'!$A$5:$A$8,0))
A8: J5 | B8: Copacabana → La Paz | C8: Manco Kapac (public) / Bolivia Hop (touristique) | D8: 155 km | E8: 3 h 30 – 4 h + barge de Tiquina | F8: BOB | G8: 30 | H8: 100 | I8: =G8/INDEX('Taux de change'!$B$5:$B$8,MATCH($F8,'Taux de change'!$A$5:$A$8,0)) | J8: =H8/INDEX('Taux de change'!$B$5:$B$8,MATCH($F8,'Taux de change'!$A$5:$A$8,0))
A9: J7 | B9: La Paz → Santa Cruz | C9: Trans Copacabana, El Dorado (bus cama) | D9: 851 km | E9: 18 h | F9: BOB | G9: 232 | H9: 319 | I9: =G9/INDEX('Taux de change'!$B$5:$B$8,MATCH($F9,'Taux de change'!$A$5:$A$8,0)) | J9: =H9/INDEX('Taux de change'!$B$5:$B$8,MATCH($F9,'Taux de change'!$A$5:$A$8,0))
A10: J8 | B10: Santa Cruz → Asunción | C10: Stel Turismo, Río Paraguay | D10: 1 324 km | E10: 24 h (Ruta Transchaco) | F10: BOB | G10: 400 | H10: 520 | I10: =G10/INDEX('Taux de change'!$B$5:$B$8,MATCH($F10,'Taux de change'!$A$5:$A$8,0)) | J10: =H10/INDEX('Taux de change'!$B$5:$B$8,MATCH($F10,'Taux de change'!$A$5:$A$8,0))
A11: J12 | B11: Asunción → São Paulo | C11: Expreso Paraguay, NSA, Pluma | D11: 1 130 km | E11: 21 h 26 | F11: PYG | G11: 450000 | H11: 620000 | I11: =G11/INDEX('Taux de change'!$B$5:$B$8,MATCH($F11,'Taux de change'!$A$5:$A$8,0)) | J11: =H11/INDEX('Taux de change'!$B$5:$B$8,MATCH($F11,'Taux de change'!$A$5:$A$8,0))
A12: J14 | B12: São Paulo → Rio | C12: Viação 1001, Cometa, Águia Branca | D12: 429 km | E12: 6 h – 6 h 45 | F12: BRL | G12: 100 | H12: 200 | I12: =G12/INDEX('Taux de change'!$B$5:$B$8,MATCH($F12,'Taux de change'!$A$5:$A$8,0)) | J12: =H12/INDEX('Taux de change'!$B$5:$B$8,MATCH($F12,'Taux de change'!$A$5:$A$8,0))
A14: TOTAL TRANSPORT LONGUE DISTANCE | I14: =SUM(I6:I12) | J14: =SUM(J6:J12)
A16: Le bus Santa Cruz → Asunción ne part que les lundi, mardi, mercredi, vendredi et samedi à 19h00 : calez votre date de départ de Lima pour que le J8 tombe un de ces jours. Achetez-le au guichet du Terminal Bimodal : les agences en ligne facturent le double.

Sheet J01 - Lima
A1: JOUR 1 — LIMA (Pérou)
A2: Lima — centre historique puis bus de nuit vers Puno
A3: Altitude : 154 m
A5: Horaires | B5: Activité / prestation | C5: Détail, vigilance, alternative | D5: Devise | E5: Coût local min | F5: Coût local max | G5: Coût USD min | H5: Coût USD max | I5: Paiement
A6: 07h30–08h15 | B6: Petit-déjeuner : café + pan con chicharrón / jugo surtido (Miraflores) | D6: PEN | E6: 8 | F6: 15 | G6: =IF($D6="","",E6/INDEX('Taux de change'!$B$5:$B$8,MATCH($D6,'Taux de change'!$A$5:$A$8,0))) | H6: =IF($D6="","",F6/INDEX('Taux de change'!$B$5:$B$8,MATCH($D6,'Taux de change'!$A$5:$A$8,0))) | I6: Espèces
A7: 08h30–09h00 | B7: Metropolitano Miraflores → Centre (station Jr. de la Unión) + achat de la carte rechargeable | C7: Carte S/ 5,40 à l'achat + S/ 3,80 le trajet. Pas de CB aux guichets. | D7: PEN | E7: 6 | F7: 10 | G7: =IF($D7="","",E7/INDEX('Taux de change'!$B$5:$B$8,MATCH($D7,'Taux de change'!$A$5:$A$8,0))) | H7: =IF($D7="","",F7/INDEX('Taux de change'!$B$5:$B$8,MATCH($D7,'Taux de change'!$A$5:$A$8,0))) | I7: Espèces
A8: 09h00–10h00 | B8: Plaza Mayor + Cathédrale de Lima (nef, crypte, musée d'art religieux) | D8: PEN | E8: 30 | F8: 30 | G8: =IF($D8="","",E8/INDEX('Taux de change'!$B$5:$B$8,MATCH($D8,'Taux de change'!$A$5:$A$8,0))) | H8: =IF($D8="","",F8/INDEX('Taux de change'!$B$5:$B$8,MATCH($D8,'Taux de change'!$A$5:$A$8,0))) | I8: CB / esp.
A9: 10h00–11h30 | B9: Couvent San Francisco + catacombes (visite guidée obligatoire, 45 min) | D9: PEN | E9: 20 | F9: 25 | G9: =IF($D9="","",E9/INDEX('Taux de change'!$B$5:$B$8,MATCH($D9,'Taux de change'!$A$5:$A$8,0))) | H9: =IF($D9="","",F9/INDEX('Taux de change'!$B$5:$B$8,MATCH($D9,'Taux de change'!$A$5:$A$8,0))) | I9: CB / esp.
A10: 11h30–12h30 | B10: Jr. de la Unión, Plaza San Martín, Casa de Aliaga (extérieur), Mercado Central | I10: —
A11: 12h30–13h30 | B11: Almuerzo « menú del día » : entrée + plat + boisson (hors zone touristique) | D11: PEN | E11: 15 | F11: 25 | G11: =IF($D11="","",E11/INDEX('Taux de change'!$B$5:$B$8,MATCH($D11,'Taux de change'!$A$5:$A$8,0))) | H11: =IF($D11="","",F11/INDEX('Taux de change'!$B$5:$B$8,MATCH($D11,'Taux de change'!$A$5:$A$8,0))) | I11: Espèces
A12: 13h30–14h30 | B12: Uber / Cabify Centre → Terrapuerto Excluciva, Av. Javier Prado Este 1155 (La Victoria) | C12: Ne pas héler un taxi dans la rue à Lima. Uber, Cabify ou InDriver uniquement. | D12: PEN | E12: 25 | F12: 40 | G12: =IF($D12="","",E12/INDEX('Taux de change'!$B$5:$B$8,MATCH($D12,'Taux de change'!$A$5:$A$8,0))) | H12: =IF($D12="","",F12/INDEX('Taux de change'!$B$5:$B$8,MATCH($D12,'Taux de change'!$A$5:$A$8,0))) | I12: CB (in-app)
A13: 14h30–15h20 | B13: Enregistrement du sac en soute + tasa de embarque | D13: PEN | E13: 2 | F13: 2 | G13: =IF($D13="","",E13/INDEX('Taux de change'!$B$5:$B$8,MATCH($D13,'Taux de change'!$A$5:$A$8,0))) | H13: =IF($D13="","",F13/INDEX('Taux de change'!$B$5:$B$8,MATCH($D13,'Taux de change'!$A$5:$A$8,0))) | I13: Espèces
A14: 15h20–15h30 | B14: Eau 2 L + snacks pour 21 h de route | D14: PEN | E14: 12 | F14: 18 | G14: =IF($D14="","",E14/INDEX('Taux de change'!$B$5:$B$8,MATCH($D14,'Taux de change'!$A$5:$A$8,0))) | H14: =IF($D14="","",F14/INDEX('Taux de change'!$B$5:$B$8,MATCH($D14,'Taux de change'!$A$5:$A$8,0))) | I14: Espèces
A15: 15h30 | B15: BUS LIMA → PUNO — Civa « Excluciva » ou Cruz del Sur « Suite » · 1 300 km · 21 h–22 h · siège 180° · 2 repas + WC + wifi aléatoire | C15: Réserver 3–7 jours à l'avance sur civa.com.pe ou cruzdelsur.com.pe. Le bus grimpe de 0 à 4 500 m dans la nuit : soroche possible au réveil. | D15: PEN | E15: 150 | F15: 230 | G15: =IF($D15="","",E15/INDEX('Taux de change'!$B$5:$B$8,MATCH($D15,'Taux de change'!$A$5:$A$8,0))) | H15: =IF($D15="","",F15/INDEX('Taux de change'!$B$5:$B$8,MATCH($D15,'Taux de change'!$A$5:$A$8,0))) | I15: CB en ligne
A16: Nuit | B16: Nuit à bord — aucune nuit d'hébergement à payer | I16: —
A18: TOTAL JOUR 1 | G18: =SUM(G6:G16) | H18: =SUM(H6:H16)
A20: Détail par devise
A21: Total S/ (PEN) | E21: =SUMIF($D$6:$D$16,"PEN",E6:E16) | F21: =SUMIF($D$6:$D$16,"PEN",F6:F16)
A23: Colonnes E et F = fourchette basse / haute en monnaie locale. Colonnes G et H = conversion automatique via la feuille « Taux de change ».

Sheet J02 - Puno
A1: JOUR 2 — PUNO (Pérou)
A2: Arrivée sur le lac Titicaca — acclimatation
A3: Altitude : 3 827 m
A5: Horaires | B5: Activité / prestation | C5: Détail, vigilance, alternative | D5: Devise | E5: Coût local min | F5: Coût local max | G5: Coût USD min | H5: Coût USD max | I5: Paiement
A6: 06h00–07h00 | B6: Petit-déjeuner servi à bord (inclus en Excluciva / Suite) — sinon arrêt Arequipa ou Juliaca | D6: PEN | E6: 0 | F6: 12 | G6: =IF($D6="","",E6/INDEX('Taux de change'!$B$5:$B$8,MATCH($D6,'Taux de change'!$A$5:$A$8,0))) | H6: =IF($D6="","",F6/INDEX('Taux de change'!$B$5:$B$8,MATCH($D6,'Taux de change'!$A$5:$A$8,0))) | I6: Espèces
A7: 12h30–13h00 | B7: Arrivée Terminal Terrestre de Puno (Jr. Primero de Mayo) | I7: —
A8: 13h00–13h20 | B8: Mototaxi terminal → centre (1,5 km) | C8: Négocier avant de monter. Course standard S/ 5. | D8: PEN | E8: 5 | F8: 8 | G8: =IF($D8="","",E8/INDEX('Taux de change'!$B$5:$B$8,MATCH($D8,'Taux de change'!$A$5:$A$8,0))) | H8: =IF($D8="","",F8/INDEX('Taux de change'!$B$5:$B$8,MATCH($D8,'Taux de change'!$A$5:$A$8,0))) | I8: Espèces
A9: 13h20–14h00 | B9: Check-in hostal, quartier Jr. Lima / Plaza de Armas — lit en dortoir (chambre privée : S/ 70–110) | D9: PEN | E9: 35 | F9: 55 | G9: =IF($D9="","",E9/INDEX('Taux de change'!$B$5:$B$8,MATCH($D9,'Taux de change'!$A$5:$A$8,0))) | H9: =IF($D9="","",F9/INDEX('Taux de change'!$B$5:$B$8,MATCH($D9,'Taux de change'!$A$5:$A$8,0))) | I9: CB / esp.
A10: 14h00–15h00 | B10: Almuerzo : trucha frita du lac + mate de coca | D10: PEN | E10: 20 | F10: 30 | G10: =IF($D10="","",E10/INDEX('Taux de change'!$B$5:$B$8,MATCH($D10,'Taux de change'!$A$5:$A$8,0))) | H10: =IF($D10="","",F10/INDEX('Taux de change'!$B$5:$B$8,MATCH($D10,'Taux de change'!$A$5:$A$8,0))) | I10: Espèces
A11: 15h00–16h00 | B11: Repos obligatoire — acclimatation. Sorojchi Pills en pharmacie (Inkafarma) | C11: Monter de 154 m à 3 827 m en une nuit : ne rien forcer le premier après-midi, boire 3 L d'eau, éviter l'alcool. | D11: PEN | E11: 12 | F11: 18 | G11: =IF($D11="","",E11/INDEX('Taux de change'!$B$5:$B$8,MATCH($D11,'Taux de change'!$A$5:$A$8,0))) | H11: =IF($D11="","",F11/INDEX('Taux de change'!$B$5:$B$8,MATCH($D11,'Taux de change'!$A$5:$A$8,0))) | I11: Espèces
A12: 16h00–17h00 | B12: Cathédrale de Puno + Plaza de Armas + Casa del Corregidor | D12: PEN | E12: 0 | F12: 10 | G12: =IF($D12="","",E12/INDEX('Taux de change'!$B$5:$B$8,MATCH($D12,'Taux de change'!$A$5:$A$8,0))) | H12: =IF($D12="","",F12/INDEX('Taux de change'!$B$5:$B$8,MATCH($D12,'Taux de change'!$A$5:$A$8,0))) | I12: Espèces
A13: 17h00–18h00 | B13: Mirador Kuntur Wasi (le condor) — mototaxi aller/retour + 100 marches | D13: PEN | E13: 10 | F13: 14 | G13: =IF($D13="","",E13/INDEX('Taux de change'!$B$5:$B$8,MATCH($D13,'Taux de change'!$A$5:$A$8,0))) | H13: =IF($D13="","",F13/INDEX('Taux de change'!$B$5:$B$8,MATCH($D13,'Taux de change'!$A$5:$A$8,0))) | I13: Espèces
A14: 18h00–18h30 | B14: Achat du billet de bus Puno → Copacabana (agence Jr. Tacna ou terminal) | C14: Trans Titicaca, Tour Perú, Trans Zela, Trans Salvador. Départ 07h30. Billet payé ici, trajet le lendemain. | D14: PEN | E14: 30 | F14: 45 | G14: =IF($D14="","",E14/INDEX('Taux de change'!$B$5:$B$8,MATCH($D14,'Taux de change'!$A$5:$A$8,0))) | H14: =IF($D14="","",F14/INDEX('Taux de change'!$B$5:$B$8,MATCH($D14,'Taux de change'!$A$5:$A$8,0))) | I14: Espèces
A15: 18h30–19h00 | B15: Change S/ → Bs en casa de cambio (Jr. Lima) et retrait DAB | C15: Frais de retrait S/ 18–25 chez BCP/Interbank. Banco de la Nación est le moins cher. Sortir de quoi tenir en Bolivie. | D15: PEN | E15: 18 | F15: 25 | G15: =IF($D15="","",E15/INDEX('Taux de change'!$B$5:$B$8,MATCH($D15,'Taux de change'!$A$5:$A$8,0))) | H15: =IF($D15="","",F15/INDEX('Taux de change'!$B$5:$B$8,MATCH($D15,'Taux de change'!$A$5:$A$8,0))) | I15: Espèces
A16: 19h30–20h30 | B16: Dîner : pizzeria au feu de bois ou anticuchos de la Plaza | D16: PEN | E16: 25 | F16: 35 | G16: =IF($D16="","",E16/INDEX('Taux de change'!$B$5:$B$8,MATCH($D16,'Taux de change'!$A$5:$A$8,0))) | H16: =IF($D16="","",F16/INDEX('Taux de change'!$B$5:$B$8,MATCH($D16,'Taux de change'!$A$5:$A$8,0))) | I16: CB / esp.
A17: — | B17: Puce Claro ou Bitel, 10 Go / 30 jours (passeport obligatoire) | D17: PEN | E17: 30 | F17: 30 | G17: =IF($D17="","",E17/INDEX('Taux de change'!$B$5:$B$8,MATCH($D17,'Taux de change'!$A$5:$A$8,0))) | H17: =IF($D17="","",F17/INDEX('Taux de change'!$B$5:$B$8,MATCH($D17,'Taux de change'!$A$5:$A$8,0))) | I17: Espèces
A19: TOTAL JOUR 2 | G19: =SUM(G6:G17) | H19: =SUM(H6:H17)
A21: Détail par devise
A22: Total S/ (PEN) | E22: =SUMIF($D$6:$D$17,"PEN",E6:E17) | F22: =SUMIF($D$6:$D$17,"PEN",F6:F17)
A24: Colonnes E et F = fourchette basse / haute en monnaie locale. Colonnes G et H = conversion automatique via la feuille « Taux de change ».

Sheet J03 - Puno-Copacabana
A1: JOUR 3 — PUNO → COPACABANA (Bolivie)
A2: Passage de frontière à Kasani — côté bolivien du Titicaca
A3: Altitude : 3 841 m
A5: Horaires | B5: Activité / prestation | C5: Détail, vigilance, alternative | D5: Devise | E5: Coût local min | F5: Coût local max | G5: Coût USD min | H5: Coût USD max | I5: Paiement
A6: 06h30–07h00 | B6: Petit-déjeuner à l'hostal (souvent inclus) | D6: PEN | E6: 0 | F6: 10 | G6: =IF($D6="","",E6/INDEX('Taux de change'!$B$5:$B$8,MATCH($D6,'Taux de change'!$A$5:$A$8,0))) | H6: =IF($D6="","",F6/INDEX('Taux de change'!$B$5:$B$8,MATCH($D6,'Taux de change'!$A$5:$A$8,0))) | I6: Espèces
A7: 07h00–07h15 | B7: Mototaxi → Terminal Terrestre | D7: PEN | E7: 5 | F7: 8 | G7: =IF($D7="","",E7/INDEX('Taux de change'!$B$5:$B$8,MATCH($D7,'Taux de change'!$A$5:$A$8,0))) | H7: =IF($D7="","",F7/INDEX('Taux de change'!$B$5:$B$8,MATCH($D7,'Taux de change'!$A$5:$A$8,0))) | I7: Espèces
A8: 07h15–07h30 | B8: Tasa de embarque du terminal de Puno | D8: PEN | E8: 1.5 | F8: 2 | G8: =IF($D8="","",E8/INDEX('Taux de change'!$B$5:$B$8,MATCH($D8,'Taux de change'!$A$5:$A$8,0))) | H8: =IF($D8="","",F8/INDEX('Taux de change'!$B$5:$B$8,MATCH($D8,'Taux de change'!$A$5:$A$8,0))) | I8: Espèces
A9: 07h30–09h30 | B9: BUS PUNO → KASANI — 150 km par la rive ouest (Chucuito, Juli, Yunguyo) | C9: Billet acheté la veille (S/ 30–45). | I9: —
A10: 09h30–10h15 | B10: FRONTIÈRE — Sortie du Pérou (Migraciones Yunguyo) : tampon de sortie | C10: Aucune taxe de sortie au Pérou. Garder la carte TAM si on vous en a donné une. | I10: GRATUIT
A11: 10h15–11h00 | B11: FRONTIÈRE — Entrée en Bolivie (Migración Kasani) : tampon 90 jours pour un passeport français | C11: Aucun visa ni frais pour les Français. Si un agent réclame une « boleta » de Bs 10–20, demandez un reçu officiel : la taxe n'existe pas. Demandez explicitement 90 jours. | I11: GRATUIT
A12: 11h00–11h15 | B12: Change $ / S/ → Bs auprès des cambistas de Kasani | C12: Taux 4–6 % moins bon qu'à La Paz : ne changez ici que Bs 300–500 de dépannage. | I12: Espèces
A13: 12h30 | B13: Arrivée Copacabana (attention : +1 h, la Bolivie est à UTC−4) | I13: —
A14: 12h30–13h00 | B14: Marche terminal → hostal (600 m, tout est à pied) | I14: —
A15: 13h00–13h30 | B15: Check-in hostal Copacabana — dortoir ou chambre privée avec vue sur le lac | C15: À Copacabana, la quasi-totalité des hostales n'acceptent QUE les espèces en bolivianos. | D15: BOB | E15: 60 | F15: 110 | G15: =IF($D15="","",E15/INDEX('Taux de change'!$B$5:$B$8,MATCH($D15,'Taux de change'!$A$5:$A$8,0))) | H15: =IF($D15="","",F15/INDEX('Taux de change'!$B$5:$B$8,MATCH($D15,'Taux de change'!$A$5:$A$8,0))) | I15: Espèces
A16: 13h30–14h30 | B16: Almuerzo : trucha a la plancha, Av. 6 de Agosto | D16: BOB | E16: 30 | F16: 45 | G16: =IF($D16="","",E16/INDEX('Taux de change'!$B$5:$B$8,MATCH($D16,'Taux de change'!$A$5:$A$8,0))) | H16: =IF($D16="","",F16/INDEX('Taux de change'!$B$5:$B$8,MATCH($D16,'Taux de change'!$A$5:$A$8,0))) | I16: Espèces
A17: 14h30–16h00 | B17: Basilique Notre-Dame de Copacabana + Capilla de Velas + bénédiction des voitures (ven./dim.) | D17: BOB | E17: 0 | F17: 10 | G17: =IF($D17="","",E17/INDEX('Taux de change'!$B$5:$B$8,MATCH($D17,'Taux de change'!$A$5:$A$8,0))) | H17: =IF($D17="","",F17/INDEX('Taux de change'!$B$5:$B$8,MATCH($D17,'Taux de change'!$A$5:$A$8,0))) | I17: Espèces
A18: 16h00–18h00 | B18: Montée au Cerro Calvario (3 966 m, 45 min) — coucher de soleil sur le Titicaca | D18: BOB | E18: 0 | F18: 5 | G18: =IF($D18="","",E18/INDEX('Taux de change'!$B$5:$B$8,MATCH($D18,'Taux de change'!$A$5:$A$8,0))) | H18: =IF($D18="","",F18/INDEX('Taux de change'!$B$5:$B$8,MATCH($D18,'Taux de change'!$A$5:$A$8,0))) | I18: Espèces
A19: 18h00–18h30 | B19: Réservation du bateau pour l'Isla del Sol au muelle (départ 08h30) | C19: Paiement le lendemain matin au guichet du quai. | I19: —
A20: 19h00–20h00 | B20: Dîner : sopa de quinua + pique macho | D20: BOB | E20: 30 | F20: 45 | G20: =IF($D20="","",E20/INDEX('Taux de change'!$B$5:$B$8,MATCH($D20,'Taux de change'!$A$5:$A$8,0))) | H20: =IF($D20="","",F20/INDEX('Taux de change'!$B$5:$B$8,MATCH($D20,'Taux de change'!$A$5:$A$8,0))) | I20: Espèces
A21: — | B21: Eau 4 L + snacks (l'eau du robinet n'est pas potable) | D21: BOB | E21: 15 | F21: 15 | G21: =IF($D21="","",E21/INDEX('Taux de change'!$B$5:$B$8,MATCH($D21,'Taux de change'!$A$5:$A$8,0))) | H21: =IF($D21="","",F21/INDEX('Taux de change'!$B$5:$B$8,MATCH($D21,'Taux de change'!$A$5:$A$8,0))) | I21: Espèces
A23: TOTAL JOUR 3 | G23: =SUM(G6:G21) | H23: =SUM(H6:H21)
A25: Détail par devise
A26: Total S/ (PEN) | E26: =SUMIF($D$6:$D$21,"PEN",E6:E21) | F26: =SUMIF($D$6:$D$21,"PEN",F6:F21)
A27: Total Bs (BOB) | E27: =SUMIF($D$6:$D$21,"BOB",E6:E21) | F27: =SUMIF($D$6:$D$21,"BOB",F6:F21)
A29: Colonnes E et F = fourchette basse / haute en monnaie locale. Colonnes G et H = conversion automatique via la feuille « Taux de change ».

Sheet J04 - Isla del Sol
A1: JOUR 4 — ISLA DEL SOL (Bolivie)
A2: Journée complète sur l'île du Soleil — berceau inca
A3: Altitude : 4 070 m
A5: Horaires | B5: Activité / prestation | C5: Détail, vigilance, alternative | D5: Devise | E5: Coût local min | F5: Coût local max | G5: Coût USD min | H5: Coût USD max | I5: Paiement
A6: 07h30–08h15 | B6: Petit-déjeuner : café + salteña | D6: BOB | E6: 12 | F6: 20 | G6: =IF($D6="","",E6/INDEX('Taux de change'!$B$5:$B$8,MATCH($D6,'Taux de change'!$A$5:$A$8,0))) | H6: =IF($D6="","",F6/INDEX('Taux de change'!$B$5:$B$8,MATCH($D6,'Taux de change'!$A$5:$A$8,0))) | I6: Espèces
A7: 08h15–08h30 | B7: Billet de bateau aller-retour au muelle (Titicaca Tours / Andes Amazonía) | C7: Bs 40 si le bateau est plein (12 pers. min.), Bs 60 sinon. Aller simple Bs 25–30. | D7: BOB | E7: 40 | F7: 60 | G7: =IF($D7="","",E7/INDEX('Taux de change'!$B$5:$B$8,MATCH($D7,'Taux de change'!$A$5:$A$8,0))) | H7: =IF($D7="","",F7/INDEX('Taux de change'!$B$5:$B$8,MATCH($D7,'Taux de change'!$A$5:$A$8,0))) | I7: Espèces
A8: 08h30–10h00 | B8: BATEAU Copacabana → Yumani (sud de l'île) — 1 h 30 de navigation | I8: —
A9: 10h00–10h15 | B9: Ticket communautaire — secteur sud (communauté de Yumani) | D9: BOB | E9: 25 | F9: 25 | G9: =IF($D9="","",E9/INDEX('Taux de change'!$B$5:$B$8,MATCH($D9,'Taux de change'!$A$5:$A$8,0))) | H9: =IF($D9="","",F9/INDEX('Taux de change'!$B$5:$B$8,MATCH($D9,'Taux de change'!$A$5:$A$8,0))) | I9: Espèces (exact)
A10: 10h15–11h15 | B10: Escalier de l'Inca (206 marches) + Fuente del Inca (3 sources) | C10: Montée très rude à 4 000 m avec le sac : laissez vos affaires à Copacabana. | I10: —
A11: 11h15–13h00 | B11: Sentier de crête sud → Pilko Kaina (temple du Soleil) + Museo de Oro | D11: BOB | E11: 15 | F11: 15 | G11: =IF($D11="","",E11/INDEX('Taux de change'!$B$5:$B$8,MATCH($D11,'Taux de change'!$A$5:$A$8,0))) | H11: =IF($D11="","",F11/INDEX('Taux de change'!$B$5:$B$8,MATCH($D11,'Taux de change'!$A$5:$A$8,0))) | I11: Espèces (exact)
A12: 13h00–14h00 | B12: Déjeuner sur l'île (trucha + vue) — prix majorés, tout est monté à dos d'âne | D12: BOB | E12: 40 | F12: 55 | G12: =IF($D12="","",E12/INDEX('Taux de change'!$B$5:$B$8,MATCH($D12,'Taux de change'!$A$5:$A$8,0))) | H12: =IF($D12="","",F12/INDEX('Taux de change'!$B$5:$B$8,MATCH($D12,'Taux de change'!$A$5:$A$8,0))) | I12: Espèces
A13: 14h00–15h00 | B13: Ticket communautaire — secteur nord (Challapampa, Roca Sagrada, Chincana) | C13: IMPORTANT : l'accès au nord de l'île est périodiquement fermé pour conflit entre communautés. Vérifiez AVANT d'acheter le bateau ; si c'est fermé, ce coût tombe. | D13: BOB | E13: 0 | F13: 25 | G13: =IF($D13="","",E13/INDEX('Taux de change'!$B$5:$B$8,MATCH($D13,'Taux de change'!$A$5:$A$8,0))) | H13: =IF($D13="","",F13/INDEX('Taux de change'!$B$5:$B$8,MATCH($D13,'Taux de change'!$A$5:$A$8,0))) | I13: Espèces (exact)
A14: 15h30–17h00 | B14: BATEAU retour Yumani → Copacabana | C14: Dernier départ 16h00 — ne pas le rater, il n'y a pas de suivant. | I14: —
A15: 17h00–18h30 | B15: Marché artisanal (alpaga, aguayos) + change complémentaire | D15: BOB | E15: 0 | F15: 80 | G15: =IF($D15="","",E15/INDEX('Taux de change'!$B$5:$B$8,MATCH($D15,'Taux de change'!$A$5:$A$8,0))) | H15: =IF($D15="","",F15/INDEX('Taux de change'!$B$5:$B$8,MATCH($D15,'Taux de change'!$A$5:$A$8,0))) | I15: Espèces
A16: 19h00–20h00 | B16: Dîner | D16: BOB | E16: 30 | F16: 45 | G16: =IF($D16="","",E16/INDEX('Taux de change'!$B$5:$B$8,MATCH($D16,'Taux de change'!$A$5:$A$8,0))) | H16: =IF($D16="","",F16/INDEX('Taux de change'!$B$5:$B$8,MATCH($D16,'Taux de change'!$A$5:$A$8,0))) | I16: Espèces
A17: Nuit | B17: Hostal Copacabana (2ᵉ nuit) | D17: BOB | E17: 60 | F17: 110 | G17: =IF($D17="","",E17/INDEX('Taux de change'!$B$5:$B$8,MATCH($D17,'Taux de change'!$A$5:$A$8,0))) | H17: =IF($D17="","",F17/INDEX('Taux de change'!$B$5:$B$8,MATCH($D17,'Taux de change'!$A$5:$A$8,0))) | I17: Espèces
A19: TOTAL JOUR 4 | G19: =SUM(G6:G17) | H19: =SUM(H6:H17)
A21: Détail par devise
A22: Total Bs (BOB) | E22: =SUMIF($D$6:$D$17,"BOB",E6:E17) | F22: =SUMIF($D$6:$D$17,"BOB",F6:F17)
A24: Colonnes E et F = fourchette basse / haute en monnaie locale. Colonnes G et H = conversion automatique via la feuille « Taux de change ».

Sheet J05 - Copacabana-La Paz
A1: JOUR 5 — COPACABANA → LA PAZ
A2: Détroit de Tiquina et descente sur La Paz
A3: Altitude : 3 640 m
A5: Horaires | B5: Activité / prestation | C5: Détail, vigilance, alternative | D5: Devise | E5: Coût local min | F5: Coût local max | G5: Coût USD min | H5: Coût USD max | I5: Paiement
A6: 07h30–08h15 | B6: Petit-déjeuner | D6: BOB | E6: 12 | F6: 20 | G6: =IF($D6="","",E6/INDEX('Taux de change'!$B$5:$B$8,MATCH($D6,'Taux de change'!$A$5:$A$8,0))) | H6: =IF($D6="","",F6/INDEX('Taux de change'!$B$5:$B$8,MATCH($D6,'Taux de change'!$A$5:$A$8,0))) | I6: Espèces
A7: 08h15–11h00 | B7: Matinée libre : Horca del Inca (observatoire pré-inca, 30 min de montée) et plage | D7: BOB | E7: 10 | F7: 15 | G7: =IF($D7="","",E7/INDEX('Taux de change'!$B$5:$B$8,MATCH($D7,'Taux de change'!$A$5:$A$8,0))) | H7: =IF($D7="","",F7/INDEX('Taux de change'!$B$5:$B$8,MATCH($D7,'Taux de change'!$A$5:$A$8,0))) | I7: Espèces
A8: 11h00–12h30 | B8: Almuerzo + courses pour la route | D8: BOB | E8: 30 | F8: 45 | G8: =IF($D8="","",E8/INDEX('Taux de change'!$B$5:$B$8,MATCH($D8,'Taux de change'!$A$5:$A$8,0))) | H8: =IF($D8="","",F8/INDEX('Taux de change'!$B$5:$B$8,MATCH($D8,'Taux de change'!$A$5:$A$8,0))) | I8: Espèces
A9: 12h30–13h15 | B9: Achat du billet — bus public (Manco Kapac, Trans Titicaca : Bs 30–40) ou bus touristique porte-à-porte (Bolivia Hop, Titicaca Bolivia : Bs 80–100) | C9: Le bus public part du parc central, le touristique vous dépose à l'hôtel à La Paz. | D9: BOB | E9: 30 | F9: 100 | G9: =IF($D9="","",E9/INDEX('Taux de change'!$B$5:$B$8,MATCH($D9,'Taux de change'!$A$5:$A$8,0))) | H9: =IF($D9="","",F9/INDEX('Taux de change'!$B$5:$B$8,MATCH($D9,'Taux de change'!$A$5:$A$8,0))) | I9: Espèces
A10: 13h30–14h45 | B10: BUS Copacabana → San Pablo de Tiquina (45 km) | I10: —
A11: 14h45–15h15 | B11: DÉTROIT DE TIQUINA — vous traversez en barque à moteur, le bus passe sur une barge en bois | C11: JAMAIS inclus dans le billet. Prévoyez la monnaie exacte, on ne rend pas. | D11: BOB | E11: 2 | F11: 3 | G11: =IF($D11="","",E11/INDEX('Taux de change'!$B$5:$B$8,MATCH($D11,'Taux de change'!$A$5:$A$8,0))) | H11: =IF($D11="","",F11/INDEX('Taux de change'!$B$5:$B$8,MATCH($D11,'Taux de change'!$A$5:$A$8,0))) | I11: Espèces (exact)
A12: 15h15–17h30 | B12: Route Tiquina → La Paz (155 km) par l'Altiplano, entrée par El Alto et la descente sur la cuvette | I12: —
A13: 17h30–18h00 | B13: Arrivée (Cementerio pour les bus publics / Terminal pour les autres) + taxi vers Sopocachi ou San Pedro | C13: Quartier Cementerio peu sûr à la nuit tombée : prenez un taxi radio, pas un taxi blanc non identifié. | D13: BOB | E13: 20 | F13: 35 | G13: =IF($D13="","",E13/INDEX('Taux de change'!$B$5:$B$8,MATCH($D13,'Taux de change'!$A$5:$A$8,0))) | H13: =IF($D13="","",F13/INDEX('Taux de change'!$B$5:$B$8,MATCH($D13,'Taux de change'!$A$5:$A$8,0))) | I13: Espèces
A14: 18h00–18h30 | B14: Check-in hostel La Paz — lit en dortoir (privée : Bs 180–280) | D14: BOB | E14: 70 | F14: 125 | G14: =IF($D14="","",E14/INDEX('Taux de change'!$B$5:$B$8,MATCH($D14,'Taux de change'!$A$5:$A$8,0))) | H14: =IF($D14="","",F14/INDEX('Taux de change'!$B$5:$B$8,MATCH($D14,'Taux de change'!$A$5:$A$8,0))) | I14: CB / esp.
A15: 19h00–20h30 | B15: Dîner à Sopocachi : plat + bière Paceña | C15: Majoration de 5 % fréquente en cas de paiement par carte. | D15: BOB | E15: 45 | F15: 70 | G15: =IF($D15="","",E15/INDEX('Taux de change'!$B$5:$B$8,MATCH($D15,'Taux de change'!$A$5:$A$8,0))) | H15: =IF($D15="","",F15/INDEX('Taux de change'!$B$5:$B$8,MATCH($D15,'Taux de change'!$A$5:$A$8,0))) | I15: CB / esp.
A16: — | B16: Retrait au DAB (BCP, Banco Unión, Mercantil Santa Cruz) | C16: Plafonds fréquents de Bs 700–2 000 par retrait et DAB souvent vides le week-end. Retirez tôt et large. | D16: BOB | E16: 25 | F16: 35 | G16: =IF($D16="","",E16/INDEX('Taux de change'!$B$5:$B$8,MATCH($D16,'Taux de change'!$A$5:$A$8,0))) | H16: =IF($D16="","",F16/INDEX('Taux de change'!$B$5:$B$8,MATCH($D16,'Taux de change'!$A$5:$A$8,0))) | I16: Espèces
A18: TOTAL JOUR 5 | G18: =SUM(G6:G16) | H18: =SUM(H6:H16)
A20: Détail par devise
A21: Total Bs (BOB) | E21: =SUMIF($D$6:$D$16,"BOB",E6:E16) | F21: =SUMIF($D$6:$D$16,"BOB",F6:F16)
A23: Colonnes E et F = fourchette basse / haute en monnaie locale. Colonnes G et H = conversion automatique via la feuille « Taux de change ».

Sheet J06 - La Paz 1
A1: JOUR 6 — LA PAZ — jour 1
A2: Téléphériques, El Alto, marchés et miradors
A3: Altitude : 3 640 m
A5: Horaires | B5: Activité / prestation | C5: Détail, vigilance, alternative | D5: Devise | E5: Coût local min | F5: Coût local max | G5: Coût USD min | H5: Coût USD max | I5: Paiement
A6: 07h30–08h30 | B6: Petit-déjeuner : api con pastel au Mercado Rodríguez | D6: BOB | E6: 10 | F6: 18 | G6: =IF($D6="","",E6/INDEX('Taux de change'!$B$5:$B$8,MATCH($D6,'Taux de change'!$A$5:$A$8,0))) | H6: =IF($D6="","",F6/INDEX('Taux de change'!$B$5:$B$8,MATCH($D6,'Taux de change'!$A$5:$A$8,0))) | I6: Espèces
A7: 09h00–12h00 | B7: Free walking tour (Red Cap Walking Tours, départ 11h00 Plaza San Pedro) — pourboire attendu | D7: BOB | E7: 50 | F7: 80 | G7: =IF($D7="","",E7/INDEX('Taux de change'!$B$5:$B$8,MATCH($D7,'Taux de change'!$A$5:$A$8,0))) | H7: =IF($D7="","",F7/INDEX('Taux de change'!$B$5:$B$8,MATCH($D7,'Taux de change'!$A$5:$A$8,0))) | I7: Espèces
A8: 12h00–12h15 | B8: Mi Teleférico — ligne Rouge : Estación Central → El Alto (16 de Julio), 4 000 m | D8: BOB | E8: 3 | F8: 3 | G8: =IF($D8="","",E8/INDEX('Taux de change'!$B$5:$B$8,MATCH($D8,'Taux de change'!$A$5:$A$8,0))) | H8: =IF($D8="","",F8/INDEX('Taux de change'!$B$5:$B$8,MATCH($D8,'Taux de change'!$A$5:$A$8,0))) | I8: Espèces / QR
A9: 12h15–13h30 | B9: Mirador d'El Alto sur toute la cuvette + Feria 16 de Julio (jeudi et dimanche, l'un des plus grands marchés d'Amérique du Sud) | C9: Pickpockets nombreux à la Feria : sac devant, pas de téléphone en main. | I9: —
A10: 13h30–14h30 | B10: Almuerzo complet (sopa + segundo + refresco) dans un comedor local | D10: BOB | E10: 20 | F10: 35 | G10: =IF($D10="","",E10/INDEX('Taux de change'!$B$5:$B$8,MATCH($D10,'Taux de change'!$A$5:$A$8,0))) | H10: =IF($D10="","",F10/INDEX('Taux de change'!$B$5:$B$8,MATCH($D10,'Taux de change'!$A$5:$A$8,0))) | I10: Espèces
A11: 14h30–14h45 | B11: Mi Teléferico — lignes Bleue puis Blanche (retour + vue sur l'Illimani) | D11: BOB | E11: 5 | F11: 6 | G11: =IF($D11="","",E11/INDEX('Taux de change'!$B$5:$B$8,MATCH($D11,'Taux de change'!$A$5:$A$8,0))) | H11: =IF($D11="","",F11/INDEX('Taux de change'!$B$5:$B$8,MATCH($D11,'Taux de change'!$A$5:$A$8,0))) | I11: Espèces / QR
A12: 15h00–16h00 | B12: Mercado de las Brujas + Calle Sagárnaga + Calle Jaén (rue coloniale) | I12: —
A13: 16h00–17h00 | B13: Musée San Francisco : cloître, catacombes, toits | D13: BOB | E13: 25 | F13: 30 | G13: =IF($D13="","",E13/INDEX('Taux de change'!$B$5:$B$8,MATCH($D13,'Taux de change'!$A$5:$A$8,0))) | H13: =IF($D13="","",F13/INDEX('Taux de change'!$B$5:$B$8,MATCH($D13,'Taux de change'!$A$5:$A$8,0))) | I13: Espèces
A14: 17h00–18h00 | B14: Museo Nacional de Etnografía y Folklore (MUSEF) | D14: BOB | E14: 20 | F14: 20 | G14: =IF($D14="","",E14/INDEX('Taux de change'!$B$5:$B$8,MATCH($D14,'Taux de change'!$A$5:$A$8,0))) | H14: =IF($D14="","",F14/INDEX('Taux de change'!$B$5:$B$8,MATCH($D14,'Taux de change'!$A$5:$A$8,0))) | I14: Espèces
A15: 18h00–18h30 | B15: Taxi → Mirador Killi Killi, coucher de soleil sur la cuvette | D15: BOB | E15: 25 | F15: 35 | G15: =IF($D15="","",E15/INDEX('Taux de change'!$B$5:$B$8,MATCH($D15,'Taux de change'!$A$5:$A$8,0))) | H15: =IF($D15="","",F15/INDEX('Taux de change'!$B$5:$B$8,MATCH($D15,'Taux de change'!$A$5:$A$8,0))) | I15: Espèces
A16: 19h30–21h00 | B16: Dîner (Popular Cocina Boliviana, Ali Pacha ou marché Sopocachi) | D16: BOB | E16: 45 | F16: 80 | G16: =IF($D16="","",E16/INDEX('Taux de change'!$B$5:$B$8,MATCH($D16,'Taux de change'!$A$5:$A$8,0))) | H16: =IF($D16="","",F16/INDEX('Taux de change'!$B$5:$B$8,MATCH($D16,'Taux de change'!$A$5:$A$8,0))) | I16: CB / esp.
A17: — | B17: ACHAT DU BILLET La Paz → Santa Cruz (Trans Copacabana, El Dorado) — bus cama, départ 19h–20h | C17: Tarif officiel homologué par l'ATT depuis le 02/01/2026 : Bs 232–308 par la route neuve, Bs 246–319 par l'ancienne. Refusez tout prix supérieur. | D17: BOB | E17: 232 | F17: 319 | G17: =IF($D17="","",E17/INDEX('Taux de change'!$B$5:$B$8,MATCH($D17,'Taux de change'!$A$5:$A$8,0))) | H17: =IF($D17="","",F17/INDEX('Taux de change'!$B$5:$B$8,MATCH($D17,'Taux de change'!$A$5:$A$8,0))) | I17: CB / esp.
A18: Nuit | B18: Hostel La Paz (2ᵉ nuit) | D18: BOB | E18: 70 | F18: 125 | G18: =IF($D18="","",E18/INDEX('Taux de change'!$B$5:$B$8,MATCH($D18,'Taux de change'!$A$5:$A$8,0))) | H18: =IF($D18="","",F18/INDEX('Taux de change'!$B$5:$B$8,MATCH($D18,'Taux de change'!$A$5:$A$8,0))) | I18: CB / esp.
A20: TOTAL JOUR 6 | G20: =SUM(G6:G18) | H20: =SUM(H6:H18)
A22: Détail par devise
A23: Total Bs (BOB) | E23: =SUMIF($D$6:$D$18,"BOB",E6:E18) | F23: =SUMIF($D$6:$D$18,"BOB",F6:F18)
A25: Colonnes E et F = fourchette basse / haute en monnaie locale. Colonnes G et H = conversion automatique via la feuille « Taux de change ».

Sheet J07 - La Paz 2
A1: JOUR 7 — LA PAZ — jour 2
A2: Route de la Mort à VTT, puis bus de nuit vers Santa Cruz
A3: Altitude : 4 650 → 1 200 m
A5: Horaires | B5: Activité / prestation | C5: Détail, vigilance, alternative | D5: Devise | E5: Coût local min | F5: Coût local max | G5: Coût USD min | H5: Coût USD max | I5: Paiement
A6: 06h45–07h15 | B6: Petit-déjeuner (inclus dans le tour) | I6: —
A7: 07h15–08h00 | B7: Ramassage à l'agence → La Cumbre (4 650 m) | I7: —
A8: 08h00–15h30 | B8: ROUTE DE LA MORT À VTT — 64 km, 3 500 m de descente, de 4 650 m à 1 200 m (Coroico/Yolosa). Inclus : VTT à double suspension, casque intégral, protections, guide, van suiveur, snacks, déjeuner, douche et T-shirt | C8: Ne prenez QUE Gravity, Vertigo, Barracuda ou Altitude : il y a des morts chaque année chez les agences à Bs 400. Payable en $ ou Bs ; carte souvent +5 %. | D8: BOB | E8: 900 | F8: 1320 | G8: =IF($D8="","",E8/INDEX('Taux de change'!$B$5:$B$8,MATCH($D8,'Taux de change'!$A$5:$A$8,0))) | H8: =IF($D8="","",F8/INDEX('Taux de change'!$B$5:$B$8,MATCH($D8,'Taux de change'!$A$5:$A$8,0))) | I8: CB / esp.
A9: — | B9: ALTERNATIVE ÉCONOMIQUE au lieu du VTT : Valle de la Luna (Bs 30) + Muela del Diablo + Valle de las Ánimas en tour partagé — Bs 150–220 ($12,5–18) | C9: Non additionné ci-dessous : si vous choisissez cette option, retirez environ Bs 900–1 320 ($75–110) du total du jour. | I9: Espèces
A10: 15h30–18h30 | B10: Retour vers La Paz (remontée par la nouvelle route des Yungas) | I10: —
A11: 18h30–19h00 | B11: Récupération des sacs à l'hostel + taxi → Terminal de Buses (Plaza Antofagasta) | D11: BOB | E11: 20 | F11: 30 | G11: =IF($D11="","",E11/INDEX('Taux de change'!$B$5:$B$8,MATCH($D11,'Taux de change'!$A$5:$A$8,0))) | H11: =IF($D11="","",F11/INDEX('Taux de change'!$B$5:$B$8,MATCH($D11,'Taux de change'!$A$5:$A$8,0))) | I11: Espèces
A12: 19h00–19h15 | B12: Tasa de uso du terminal de La Paz | D12: BOB | E12: 2.5 | F12: 3.5 | G12: =IF($D12="","",E12/INDEX('Taux de change'!$B$5:$B$8,MATCH($D12,'Taux de change'!$A$5:$A$8,0))) | H12: =IF($D12="","",F12/INDEX('Taux de change'!$B$5:$B$8,MATCH($D12,'Taux de change'!$A$5:$A$8,0))) | I12: Espèces (exact)
A13: 19h15–19h45 | B13: Courses pour 18 h de route : 3 L d'eau, pain, fruits secs, papier toilette | D13: BOB | E13: 25 | F13: 40 | G13: =IF($D13="","",E13/INDEX('Taux de change'!$B$5:$B$8,MATCH($D13,'Taux de change'!$A$5:$A$8,0))) | H13: =IF($D13="","",F13/INDEX('Taux de change'!$B$5:$B$8,MATCH($D13,'Taux de change'!$A$5:$A$8,0))) | I13: Espèces
A14: 20h00 | B14: BUS LA PAZ → SANTA CRUZ — 851 km, ~18 h, bus cama. Descente de 3 640 m à 416 m | C14: Billet payé la veille. Couverture indispensable : les 6 premières heures sont glaciales, les 6 dernières tropicales. | I14: —
A15: Nuit | B15: Nuit à bord | I15: —
A17: TOTAL JOUR 7 | G17: =SUM(G6:G15) | H17: =SUM(H6:H15)
A19: Détail par devise
A20: Total Bs (BOB) | E20: =SUMIF($D$6:$D$15,"BOB",E6:E15) | F20: =SUMIF($D$6:$D$15,"BOB",F6:F15)
A22: Colonnes E et F = fourchette basse / haute en monnaie locale. Colonnes G et H = conversion automatique via la feuille « Taux de change ».

Sheet J08 - Santa Cruz
A1: JOUR 8 — SANTA CRUZ (transit)
A2: Escale de 6 h puis départ pour le Chaco
A3: Altitude : 416 m
A5: Horaires | B5: Activité / prestation | C5: Détail, vigilance, alternative | D5: Devise | E5: Coût local min | F5: Coût local max | G5: Coût USD min | H5: Coût USD max | I5: Paiement
A6: 13h00–13h30 | B6: Arrivée Terminal Bimodal de Santa Cruz (chaleur 30–34 °C, humidité) | I6: —
A7: 13h30–13h45 | B7: Consigne à bagages (guarda equipaje), 6 h | D7: BOB | E7: 15 | F7: 25 | G7: =IF($D7="","",E7/INDEX('Taux de change'!$B$5:$B$8,MATCH($D7,'Taux de change'!$A$5:$A$8,0))) | H7: =IF($D7="","",F7/INDEX('Taux de change'!$B$5:$B$8,MATCH($D7,'Taux de change'!$A$5:$A$8,0))) | I7: Espèces
A8: 13h45–14h15 | B8: ACHAT DU BILLET Santa Cruz → Asunción — Stel Turismo ou Río Paraguay, départ 19h00 (lun, mar, mer, ven, sam) | C8: Prix au guichet du terminal. Les agences internationales en ligne (Busbud, Plataforma10) affichent $85–100 pour le même siège : achetez sur place. Réservez dès votre arrivée le matin, il n'y a qu'un départ par jour. | D8: BOB | E8: 400 | F8: 520 | G8: =IF($D8="","",E8/INDEX('Taux de change'!$B$5:$B$8,MATCH($D8,'Taux de change'!$A$5:$A$8,0))) | H8: =IF($D8="","",F8/INDEX('Taux de change'!$B$5:$B$8,MATCH($D8,'Taux de change'!$A$5:$A$8,0))) | I8: Espèces
A9: 14h15–15h00 | B9: Micro n° 12 ou taxi → Plaza 24 de Septiembre | D9: BOB | E9: 2.3 | F9: 30 | G9: =IF($D9="","",E9/INDEX('Taux de change'!$B$5:$B$8,MATCH($D9,'Taux de change'!$A$5:$A$8,0))) | H9: =IF($D9="","",F9/INDEX('Taux de change'!$B$5:$B$8,MATCH($D9,'Taux de change'!$A$5:$A$8,0))) | I9: Espèces
A10: 15h00–16h00 | B10: Almuerzo cruceño : majadito ou pollo a la broaster | D10: BOB | E10: 30 | F10: 45 | G10: =IF($D10="","",E10/INDEX('Taux de change'!$B$5:$B$8,MATCH($D10,'Taux de change'!$A$5:$A$8,0))) | H10: =IF($D10="","",F10/INDEX('Taux de change'!$B$5:$B$8,MATCH($D10,'Taux de change'!$A$5:$A$8,0))) | I10: Espèces
A11: 16h00–17h30 | B11: Catedral Basílica de San Lorenzo (montée au clocher) + Casco Viejo + Manzana Uno | D11: BOB | E11: 10 | F11: 20 | G11: =IF($D11="","",E11/INDEX('Taux de change'!$B$5:$B$8,MATCH($D11,'Taux de change'!$A$5:$A$8,0))) | H11: =IF($D11="","",F11/INDEX('Taux de change'!$B$5:$B$8,MATCH($D11,'Taux de change'!$A$5:$A$8,0))) | I11: Espèces
A12: 17h30–18h00 | B12: Retour au terminal + récupération des sacs | D12: BOB | E12: 10 | F12: 30 | G12: =IF($D12="","",E12/INDEX('Taux de change'!$B$5:$B$8,MATCH($D12,'Taux de change'!$A$5:$A$8,0))) | H12: =IF($D12="","",F12/INDEX('Taux de change'!$B$5:$B$8,MATCH($D12,'Taux de change'!$A$5:$A$8,0))) | I12: Espèces
A13: 18h00–18h45 | B13: PROVISIONS OBLIGATOIRES POUR LE CHACO : 5–6 L d'eau, pain, fruits secs, papier toilette, gel hydroalcoolique, répulsif | C13: 24 h de route dans le Chaco sec : quasiment aucun service entre Villamontes et Mariscal Estigarribia. | D13: BOB | E13: 60 | F13: 90 | G13: =IF($D13="","",E13/INDEX('Taux de change'!$B$5:$B$8,MATCH($D13,'Taux de change'!$A$5:$A$8,0))) | H13: =IF($D13="","",F13/INDEX('Taux de change'!$B$5:$B$8,MATCH($D13,'Taux de change'!$A$5:$A$8,0))) | I13: Espèces
A14: 18h45–19h00 | B14: Tasa de uso du Terminal Bimodal | D14: BOB | E14: 5 | F14: 8 | G14: =IF($D14="","",E14/INDEX('Taux de change'!$B$5:$B$8,MATCH($D14,'Taux de change'!$A$5:$A$8,0))) | H14: =IF($D14="","",F14/INDEX('Taux de change'!$B$5:$B$8,MATCH($D14,'Taux de change'!$A$5:$A$8,0))) | I14: Espèces (exact)
A15: 19h00 | B15: BUS SANTA CRUZ → ASUNCIÓN — 1 324 km, ~24 h, via Abapó, Camiri, Villamontes, Ruta Transchaco | C15: Billet payé le matin. Route partiellement dégradée après Villamontes, climatisation aléatoire. | I15: —
A16: — | B16: CONTRÔLE : carnet de vaccination fièvre jaune exigé à l'entrée au Paraguay (voir Annexe B) | I16: —
A18: TOTAL JOUR 8 | G18: =SUM(G6:G16) | H18: =SUM(H6:H16)
A20: Détail par devise
A21: Total Bs (BOB) | E21: =SUMIF($D$6:$D$16,"BOB",E6:E16) | F21: =SUMIF($D$6:$D$16,"BOB",F6:F16)
A23: Colonnes E et F = fourchette basse / haute en monnaie locale. Colonnes G et H = conversion automatique via la feuille « Taux de change ».

Sheet J09 - Chaco-Asuncion
A1: JOUR 9 — CHACO → ASUNCIÓN (Paraguay)
A2: Traversée du Chaco et double frontière
A3: Altitude : 43 m
A5: Horaires | B5: Activité / prestation | C5: Détail, vigilance, alternative | D5: Devise | E5: Coût local min | F5: Coût local max | G5: Coût USD min | H5: Coût USD max | I5: Paiement
A6: 05h00–06h00 | B6: Arrêt petit-déjeuner à Villamontes | C6: Dernière occasion de dépenser vos bolivianos : ils ne valent rien au Paraguay. | D6: BOB | E6: 15 | F6: 25 | G6: =IF($D6="","",E6/INDEX('Taux de change'!$B$5:$B$8,MATCH($D6,'Taux de change'!$A$5:$A$8,0))) | H6: =IF($D6="","",F6/INDEX('Taux de change'!$B$5:$B$8,MATCH($D6,'Taux de change'!$A$5:$A$8,0))) | I6: Espèces
A7: 07h00–08h30 | B7: FRONTIÈRE — Sortie de Bolivie (poste d'Ibibobo / Villamontes) : tampon de sortie | C7: Aucune taxe de sortie officielle. Refusez poliment toute demande de « propina ». | I7: GRATUIT
A8: 08h30–10h00 | B8: No man's land d'Infante Rivarola — 100 km de Chaco sec, aucun service | I8: —
A9: 10h00–12h00 | B9: FRONTIÈRE — Entrée au Paraguay (Migraciones + contrôle sanitaire + fouille douanière) | C9: Pas de visa ni de frais pour les Français (90 jours). CARNET INTERNATIONAL DE VACCINATION FIÈVRE JAUNE OBLIGATOIRE (Résolution 268/2025) car vous venez du département de Santa Cruz, classé zone à risque. | I9: GRATUIT
A10: 12h00–13h00 | B10: Déjeuner à Mariscal Estigarribia ou Filadelfia (colonie mennonite) : empanadas, sopa paraguaya | D10: PYG | E10: 25000 | F10: 45000 | G10: =IF($D10="","",E10/INDEX('Taux de change'!$B$5:$B$8,MATCH($D10,'Taux de change'!$A$5:$A$8,0))) | H10: =IF($D10="","",F10/INDEX('Taux de change'!$B$5:$B$8,MATCH($D10,'Taux de change'!$A$5:$A$8,0))) | I10: Espèces
A11: 13h00–19h00 | B11: Ruta Transchaco : Loma Plata, Pozo Colorado, Villa Hayes, traversée du fleuve Paraguay | I11: —
A12: 19h00–20h00 | B12: Arrivée Terminal de Ómnibus de Asunción (Av. Fernando de la Mora) | C12: Le Paraguay est à UTC−3 : +1 h par rapport à la Bolivie. | I12: —
A13: 20h00–20h30 | B13: Bolt ou Uber terminal → centre / Villa Morra (6 km) | C13: Bolt est 20–30 % moins cher qu'Uber à Asunción. Taxi de rue : Gs 70 000–90 000 pour le même trajet. | D13: PYG | E13: 30000 | F13: 45000 | G13: =IF($D13="","",E13/INDEX('Taux de change'!$B$5:$B$8,MATCH($D13,'Taux de change'!$A$5:$A$8,0))) | H13: =IF($D13="","",F13/INDEX('Taux de change'!$B$5:$B$8,MATCH($D13,'Taux de change'!$A$5:$A$8,0))) | I13: CB (in-app)
A14: 20h30–21h00 | B14: Check-in hostel Asunción — lit en dortoir (privée : Gs 200 000–280 000) | D14: PYG | E14: 90000 | F14: 150000 | G14: =IF($D14="","",E14/INDEX('Taux de change'!$B$5:$B$8,MATCH($D14,'Taux de change'!$A$5:$A$8,0))) | H14: =IF($D14="","",F14/INDEX('Taux de change'!$B$5:$B$8,MATCH($D14,'Taux de change'!$A$5:$A$8,0))) | I14: CB / esp.
A15: 21h00–22h00 | B15: Dîner : asado ou lomito árabe + tereré | D15: PYG | E15: 45000 | F15: 75000 | G15: =IF($D15="","",E15/INDEX('Taux de change'!$B$5:$B$8,MATCH($D15,'Taux de change'!$A$5:$A$8,0))) | H15: =IF($D15="","",F15/INDEX('Taux de change'!$B$5:$B$8,MATCH($D15,'Taux de change'!$A$5:$A$8,0))) | I15: CB / esp.
A17: TOTAL JOUR 9 | G17: =SUM(G6:G15) | H17: =SUM(H6:H15)
A19: Détail par devise
A20: Total Bs (BOB) | E20: =SUMIF($D$6:$D$15,"BOB",E6:E15) | F20: =SUMIF($D$6:$D$15,"BOB",F6:F15)
A21: Total Gs (PYG) | E21: =SUMIF($D$6:$D$15,"PYG",E6:E15) | F21: =SUMIF($D$6:$D$15,"PYG",F6:F15)
A23: Colonnes E et F = fourchette basse / haute en monnaie locale. Colonnes G et H = conversion automatique via la feuille « Taux de change ».

Sheet J10 - Asuncion 1
A1: JOUR 10 — ASUNCIÓN — jour 1
A2: Centre historique, Mercado 4 et Costanera
A3: Altitude : 43 m
A5: Horaires | B5: Activité / prestation | C5: Détail, vigilance, alternative | D5: Devise | E5: Coût local min | F5: Coût local max | G5: Coût USD min | H5: Coût USD max | I5: Paiement
A6: 07h30–08h30 | B6: Petit-déjeuner : cocido quemado + chipa | D6: PYG | E6: 15000 | F6: 25000 | G6: =IF($D6="","",E6/INDEX('Taux de change'!$B$5:$B$8,MATCH($D6,'Taux de change'!$A$5:$A$8,0))) | H6: =IF($D6="","",F6/INDEX('Taux de change'!$B$5:$B$8,MATCH($D6,'Taux de change'!$A$5:$A$8,0))) | I6: Espèces
A7: 08h30–09h00 | B7: Bus urbain (ligne 30) ou Bolt → centre historique | C7: Les bus urbains d'Asunción n'acceptent plus les espèces : il faut la carte rechargeable « Billetaje Electrónico » (Gs 10 000 la carte). En pratique, Bolt est plus simple pour 2 jours. | D7: PYG | E7: 3500 | F7: 25000 | G7: =IF($D7="","",E7/INDEX('Taux de change'!$B$5:$B$8,MATCH($D7,'Taux de change'!$A$5:$A$8,0))) | H7: =IF($D7="","",F7/INDEX('Taux de change'!$B$5:$B$8,MATCH($D7,'Taux de change'!$A$5:$A$8,0))) | I7: Carte Más / CB
A8: 09h00–09h45 | B8: Panteón Nacional de los Héroes (gratuit, don bienvenu) + relève de la garde | D8: PYG | E8: 0 | F8: 10000 | G8: =IF($D8="","",E8/INDEX('Taux de change'!$B$5:$B$8,MATCH($D8,'Taux de change'!$A$5:$A$8,0))) | H8: =IF($D8="","",F8/INDEX('Taux de change'!$B$5:$B$8,MATCH($D8,'Taux de change'!$A$5:$A$8,0))) | I8: Espèces
A9: 09h45–10h30 | B9: Casa de la Independencia (1772) — gratuit | I9: —
A10: 10h30–11h15 | B10: Cabildo / Centro Cultural de la República — gratuit | I10: —
A11: 11h15–12h00 | B11: Palacio de los López (extérieur) + promenade sur la Costanera | I11: —
A12: 12h00–13h00 | B12: Almuerzo au Mercado 4 : bife koygua, sopa paraguaya, mbejú | D12: PYG | E12: 30000 | F12: 50000 | G12: =IF($D12="","",E12/INDEX('Taux de change'!$B$5:$B$8,MATCH($D12,'Taux de change'!$A$5:$A$8,0))) | H12: =IF($D12="","",F12/INDEX('Taux de change'!$B$5:$B$8,MATCH($D12,'Taux de change'!$A$5:$A$8,0))) | I12: Espèces
A13: 13h00–14h30 | B13: Mercado 4 : herbes médicinales (pohã ñana), artisanat ñandutí, cuir | D13: PYG | E13: 0 | F13: 60000 | G13: =IF($D13="","",E13/INDEX('Taux de change'!$B$5:$B$8,MATCH($D13,'Taux de change'!$A$5:$A$8,0))) | H13: =IF($D13="","",F13/INDEX('Taux de change'!$B$5:$B$8,MATCH($D13,'Taux de change'!$A$5:$A$8,0))) | I13: Espèces
A14: 15h00–17h00 | B14: Museo del Barro — art indigène, populaire et contemporain (le meilleur musée du pays) | C14: Entrée gratuite le vendredi et le samedi. Ouvert mar.–sam. 14h–20h uniquement. | D14: PYG | E14: 0 | F14: 50000 | G14: =IF($D14="","",E14/INDEX('Taux de change'!$B$5:$B$8,MATCH($D14,'Taux de change'!$A$5:$A$8,0))) | H14: =IF($D14="","",F14/INDEX('Taux de change'!$B$5:$B$8,MATCH($D14,'Taux de change'!$A$5:$A$8,0))) | I14: CB / esp.
A15: 17h00–18h30 | B15: Loma San Jerónimo (quartier coloré en escaliers) — Bolt aller/retour | D15: PYG | E15: 40000 | F15: 60000 | G15: =IF($D15="","",E15/INDEX('Taux de change'!$B$5:$B$8,MATCH($D15,'Taux de change'!$A$5:$A$8,0))) | H15: =IF($D15="","",F15/INDEX('Taux de change'!$B$5:$B$8,MATCH($D15,'Taux de change'!$A$5:$A$8,0))) | I15: CB (in-app)
A16: 19h00–20h00 | B16: Coucher de soleil sur la Bahía + tereré glacé | D16: PYG | E16: 10000 | F16: 20000 | G16: =IF($D16="","",E16/INDEX('Taux de change'!$B$5:$B$8,MATCH($D16,'Taux de change'!$A$5:$A$8,0))) | H16: =IF($D16="","",F16/INDEX('Taux de change'!$B$5:$B$8,MATCH($D16,'Taux de change'!$A$5:$A$8,0))) | I16: Espèces
A17: 20h30–22h00 | B17: Dîner : Lido Bar (face au Panthéon) ou Paulista Grill (rodízio) | D17: PYG | E17: 60000 | F17: 110000 | G17: =IF($D17="","",E17/INDEX('Taux de change'!$B$5:$B$8,MATCH($D17,'Taux de change'!$A$5:$A$8,0))) | H17: =IF($D17="","",F17/INDEX('Taux de change'!$B$5:$B$8,MATCH($D17,'Taux de change'!$A$5:$A$8,0))) | I17: CB
A18: Nuit | B18: Hostel Asunción (2ᵉ nuit) | D18: PYG | E18: 90000 | F18: 150000 | G18: =IF($D18="","",E18/INDEX('Taux de change'!$B$5:$B$8,MATCH($D18,'Taux de change'!$A$5:$A$8,0))) | H18: =IF($D18="","",F18/INDEX('Taux de change'!$B$5:$B$8,MATCH($D18,'Taux de change'!$A$5:$A$8,0))) | I18: CB / esp.
A20: TOTAL JOUR 10 | G20: =SUM(G6:G18) | H20: =SUM(H6:H18)
A22: Détail par devise
A23: Total Gs (PYG) | E23: =SUMIF($D$6:$D$18,"PYG",E6:E18) | F23: =SUMIF($D$6:$D$18,"PYG",F6:F18)
A25: Colonnes E et F = fourchette basse / haute en monnaie locale. Colonnes G et H = conversion automatique via la feuille « Taux de change ».

Sheet J11 - Asuncion 2
A1: JOUR 11 — ASUNCIÓN — jour 2
A2: Lac Ypacaraí (Areguá) et préparation du grand bus
A3: Altitude : 43 m
A5: Horaires | B5: Activité / prestation | C5: Détail, vigilance, alternative | D5: Devise | E5: Coût local min | F5: Coût local max | G5: Coût USD min | H5: Coût USD max | I5: Paiement
A6: 07h30–08h15 | B6: Petit-déjeuner | D6: PYG | E6: 15000 | F6: 25000 | G6: =IF($D6="","",E6/INDEX('Taux de change'!$B$5:$B$8,MATCH($D6,'Taux de change'!$A$5:$A$8,0))) | H6: =IF($D6="","",F6/INDEX('Taux de change'!$B$5:$B$8,MATCH($D6,'Taux de change'!$A$5:$A$8,0))) | I6: Espèces
A7: 08h30–09h30 | B7: Bus interurbain Asunción → Areguá (30 km, village des céramistes au bord du lac Ypacaraí) | D7: PYG | E7: 8000 | F7: 15000 | G7: =IF($D7="","",E7/INDEX('Taux de change'!$B$5:$B$8,MATCH($D7,'Taux de change'!$A$5:$A$8,0))) | H7: =IF($D7="","",F7/INDEX('Taux de change'!$B$5:$B$8,MATCH($D7,'Taux de change'!$A$5:$A$8,0))) | I7: Espèces
A8: 09h30–12h30 | B8: Areguá : église Nuestra Señora de la Candelaria, ateliers de céramique, mirador sur le lac, maisons coloniales | D8: PYG | E8: 0 | F8: 20000 | G8: =IF($D8="","",E8/INDEX('Taux de change'!$B$5:$B$8,MATCH($D8,'Taux de change'!$A$5:$A$8,0))) | H8: =IF($D8="","",F8/INDEX('Taux de change'!$B$5:$B$8,MATCH($D8,'Taux de change'!$A$5:$A$8,0))) | I8: Espèces
A9: 12h30–13h30 | B9: Déjeuner à Areguá (poisson du lac) | D9: PYG | E9: 30000 | F9: 50000 | G9: =IF($D9="","",E9/INDEX('Taux de change'!$B$5:$B$8,MATCH($D9,'Taux de change'!$A$5:$A$8,0))) | H9: =IF($D9="","",F9/INDEX('Taux de change'!$B$5:$B$8,MATCH($D9,'Taux de change'!$A$5:$A$8,0))) | I9: Espèces
A10: 13h30–15h00 | B10: Bus retour vers Asunción | D10: PYG | E10: 8000 | F10: 15000 | G10: =IF($D10="","",E10/INDEX('Taux de change'!$B$5:$B$8,MATCH($D10,'Taux de change'!$A$5:$A$8,0))) | H10: =IF($D10="","",F10/INDEX('Taux de change'!$B$5:$B$8,MATCH($D10,'Taux de change'!$A$5:$A$8,0))) | I10: Espèces
A11: 15h30–17h00 | B11: Manzana de la Rivera + Estación Central del Ferrocarril (1861, 1ʳᵉ gare d'Amérique du Sud) | D11: PYG | E11: 5000 | F11: 15000 | G11: =IF($D11="","",E11/INDEX('Taux de change'!$B$5:$B$8,MATCH($D11,'Taux de change'!$A$5:$A$8,0))) | H11: =IF($D11="","",F11/INDEX('Taux de change'!$B$5:$B$8,MATCH($D11,'Taux de change'!$A$5:$A$8,0))) | I11: Espèces
A12: 17h00–18h00 | B12: ACHAT DU BILLET Asunción → São Paulo au guichet du Terminal (Expreso Paraguay, Nuestra Señora de la Asunción, Pluma) | C12: $76–105 selon la classe (semi-cama / cama). Expreso Paraguay part à 07h00 et arrive à 04h26 (21 h 26). Départ à 09h20 avec Expresso Nordeste (plus long). | D12: PYG | E12: 450000 | F12: 620000 | G12: =IF($D12="","",E12/INDEX('Taux de change'!$B$5:$B$8,MATCH($D12,'Taux de change'!$A$5:$A$8,0))) | H12: =IF($D12="","",F12/INDEX('Taux de change'!$B$5:$B$8,MATCH($D12,'Taux de change'!$A$5:$A$8,0))) | I12: CB / esp.
A13: 18h00–19h00 | B13: Shopping Ciudad Nueva / pharmacie — le Paraguay est le pays le moins cher du continent pour l'électronique et les médicaments | D13: PYG | E13: 0 | F13: 100000 | G13: =IF($D13="","",E13/INDEX('Taux de change'!$B$5:$B$8,MATCH($D13,'Taux de change'!$A$5:$A$8,0))) | H13: =IF($D13="","",F13/INDEX('Taux de change'!$B$5:$B$8,MATCH($D13,'Taux de change'!$A$5:$A$8,0))) | I13: CB
A14: 19h30–21h00 | B14: Dîner d'adieu (chipa guazú, asado) | D14: PYG | E14: 60000 | F14: 110000 | G14: =IF($D14="","",E14/INDEX('Taux de change'!$B$5:$B$8,MATCH($D14,'Taux de change'!$A$5:$A$8,0))) | H14: =IF($D14="","",F14/INDEX('Taux de change'!$B$5:$B$8,MATCH($D14,'Taux de change'!$A$5:$A$8,0))) | I14: CB
A15: Nuit | B15: Hostel Asunción (3ᵉ nuit) | D15: PYG | E15: 90000 | F15: 150000 | G15: =IF($D15="","",E15/INDEX('Taux de change'!$B$5:$B$8,MATCH($D15,'Taux de change'!$A$5:$A$8,0))) | H15: =IF($D15="","",F15/INDEX('Taux de change'!$B$5:$B$8,MATCH($D15,'Taux de change'!$A$5:$A$8,0))) | I15: CB / esp.
A17: TOTAL JOUR 11 | G17: =SUM(G6:G15) | H17: =SUM(H6:H15)
A19: Détail par devise
A20: Total Gs (PYG) | E20: =SUMIF($D$6:$D$15,"PYG",E6:E15) | F20: =SUMIF($D$6:$D$15,"PYG",F6:F15)
A22: Colonnes E et F = fourchette basse / haute en monnaie locale. Colonnes G et H = conversion automatique via la feuille « Taux de change ».

Sheet J12 - Asuncion-Sao Paulo
A1: JOUR 12 — ASUNCIÓN → SÃO PAULO
A2: 21 h 30 de bus et passage au Brésil par le Pont de l'Amitié
A3: Altitude : —
A5: Horaires | B5: Activité / prestation | C5: Détail, vigilance, alternative | D5: Devise | E5: Coût local min | F5: Coût local max | G5: Coût USD min | H5: Coût USD max | I5: Paiement
A6: 05h30–06h00 | B6: Café à l'hostel | D6: PYG | E6: 10000 | F6: 20000 | G6: =IF($D6="","",E6/INDEX('Taux de change'!$B$5:$B$8,MATCH($D6,'Taux de change'!$A$5:$A$8,0))) | H6: =IF($D6="","",F6/INDEX('Taux de change'!$B$5:$B$8,MATCH($D6,'Taux de change'!$A$5:$A$8,0))) | I6: Espèces
A7: 06h00–06h30 | B7: Bolt → Terminal de Ómnibus de Asunción | D7: PYG | E7: 30000 | F7: 45000 | G7: =IF($D7="","",E7/INDEX('Taux de change'!$B$5:$B$8,MATCH($D7,'Taux de change'!$A$5:$A$8,0))) | H7: =IF($D7="","",F7/INDEX('Taux de change'!$B$5:$B$8,MATCH($D7,'Taux de change'!$A$5:$A$8,0))) | I7: CB (in-app)
A8: 06h30–07h00 | B8: Tasa de terminal + enregistrement des bagages en soute | D8: PYG | E8: 5000 | F8: 15000 | G8: =IF($D8="","",E8/INDEX('Taux de change'!$B$5:$B$8,MATCH($D8,'Taux de change'!$A$5:$A$8,0))) | H8: =IF($D8="","",F8/INDEX('Taux de change'!$B$5:$B$8,MATCH($D8,'Taux de change'!$A$5:$A$8,0))) | I8: Espèces
A9: 07h00 | B9: BUS ASUNCIÓN → SÃO PAULO — Expreso Paraguay · 1 130 km · 21 h 26 · via Coronel Oviedo, Ciudad del Este, Foz do Iguaçu, Cascavel, Curitiba | C9: Billet payé la veille. | I9: —
A10: 12h30–14h30 | B10: FRONTIÈRE — Ciudad del Este / Foz do Iguaçu (Puente de la Amistad) : descente avec TOUS les bagages, tampon de sortie du Paraguay puis tampon d'entrée au Brésil | C10: Aucun frais ni visa pour les Français (90 jours). EXIGEZ LES DEUX TAMPONS : beaucoup de bus ne s'arrêtent que côté brésilien et l'absence de tampon de sortie paraguayen vous coûtera une amende plus tard. Comptez 1 h 30–2 h. | I10: GRATUIT
A11: 14h30–15h00 | B11: Change Gs → R$ ou retrait à Foz do Iguaçu | C11: Dépensez vos derniers guaranis : ils sont inéchangeables hors du Paraguay. | I11: Espèces
A12: 15h00–16h00 | B12: Déjeuner à l'arrêt (Foz do Iguaçu ou Cascavel) — restaurant por quilo | D12: BRL | E12: 30 | F12: 50 | G12: =IF($D12="","",E12/INDEX('Taux de change'!$B$5:$B$8,MATCH($D12,'Taux de change'!$A$5:$A$8,0))) | H12: =IF($D12="","",F12/INDEX('Taux de change'!$B$5:$B$8,MATCH($D12,'Taux de change'!$A$5:$A$8,0))) | I12: CB
A13: 20h00–21h00 | B13: Dîner à l'arrêt routier | D13: BRL | E13: 25 | F13: 45 | G13: =IF($D13="","",E13/INDEX('Taux de change'!$B$5:$B$8,MATCH($D13,'Taux de change'!$A$5:$A$8,0))) | H13: =IF($D13="","",F13/INDEX('Taux de change'!$B$5:$B$8,MATCH($D13,'Taux de change'!$A$5:$A$8,0))) | I13: CB
A14: Nuit | B14: Nuit à bord | I14: —
A16: TOTAL JOUR 12 | G16: =SUM(G6:G14) | H16: =SUM(H6:H14)
A18: Détail par devise
A19: Total Gs (PYG) | E19: =SUMIF($D$6:$D$14,"PYG",E6:E14) | F19: =SUMIF($D$6:$D$14,"PYG",F6:F14)
A20: Total R$ (BRL) | E20: =SUMIF($D$6:$D$14,"BRL",E6:E14) | F20: =SUMIF($D$6:$D$14,"BRL",F6:F14)
A22: Colonnes E et F = fourchette basse / haute en monnaie locale. Colonnes G et H = conversion automatique via la feuille « Taux de change ».

Sheet J13 - Sao Paulo 1
A1: JOUR 13 — SÃO PAULO — jour 1
A2: Arrivée à l'aube, Avenida Paulista et centre
A3: Altitude : 760 m
A5: Horaires | B5: Activité / prestation | C5: Détail, vigilance, alternative | D5: Devise | E5: Coût local min | F5: Coût local max | G5: Coût USD min | H5: Coût USD max | I5: Paiement
A6: 04h26–05h00 | B6: Arrivée Terminal Rodoviário Tietê | I6: —
A7: 05h00–05h30 | B7: Café + attente de l'ouverture du métro (04h40 en semaine, 06h00 le dimanche) | D7: BRL | E7: 10 | F7: 18 | G7: =IF($D7="","",E7/INDEX('Taux de change'!$B$5:$B$8,MATCH($D7,'Taux de change'!$A$5:$A$8,0))) | H7: =IF($D7="","",F7/INDEX('Taux de change'!$B$5:$B$8,MATCH($D7,'Taux de change'!$A$5:$A$8,0))) | I7: CB / PIX
A8: 05h30–06h00 | B8: Métro ligne 1 Bleue : Tietê → República ou Paraíso | C8: Tarif unique 2026 : R$ 5,40. On paie directement avec une carte bancaire sans contact aux tourniquets — pas besoin de Bilhete Único. | D8: BRL | E8: 5.4 | F8: 5.4 | G8: =IF($D8="","",E8/INDEX('Taux de change'!$B$5:$B$8,MATCH($D8,'Taux de change'!$A$5:$A$8,0))) | H8: =IF($D8="","",F8/INDEX('Taux de change'!$B$5:$B$8,MATCH($D8,'Taux de change'!$A$5:$A$8,0))) | I8: CB sans contact
A9: 06h00–08h00 | B9: Dépôt des sacs à l'auberge (check-in à 14h) puis douche si l'auberge le permet | I9: —
A10: 08h00–09h00 | B10: Petit-déjeuner en padaria : pão na chapa + pingado + pastel de nata | D10: BRL | E10: 15 | F10: 25 | G10: =IF($D10="","",E10/INDEX('Taux de change'!$B$5:$B$8,MATCH($D10,'Taux de change'!$A$5:$A$8,0))) | H10: =IF($D10="","",F10/INDEX('Taux de change'!$B$5:$B$8,MATCH($D10,'Taux de change'!$A$5:$A$8,0))) | I10: CB / PIX
A11: 09h00–10h30 | B11: Avenida Paulista + Parque Trianon (gratuit) + Casa das Rosas | I11: —
A12: 10h30–12h30 | B12: MASP — Museu de Arte de São Paulo (chevalets de verre de Lina Bo Bardi) | C12: R$ 80 le lun./mer./jeu., R$ 100 le ven./sam./dim. et jours fériés, et gratuit le mardi (opération Nubank). Vérifiez le jour de fermeture hebdomadaire sur masp.org.br avant de vous déplacer. | D12: BRL | E12: 0 | F12: 100 | G12: =IF($D12="","",E12/INDEX('Taux de change'!$B$5:$B$8,MATCH($D12,'Taux de change'!$A$5:$A$8,0))) | H12: =IF($D12="","",F12/INDEX('Taux de change'!$B$5:$B$8,MATCH($D12,'Taux de change'!$A$5:$A$8,0))) | I12: CB
A13: 12h30–13h30 | B13: Almoço por quilo sur la Paulista (R$ 75–95 le kilo, ~450 g par assiette) | D13: BRL | E13: 40 | F13: 60 | G13: =IF($D13="","",E13/INDEX('Taux de change'!$B$5:$B$8,MATCH($D13,'Taux de change'!$A$5:$A$8,0))) | H13: =IF($D13="","",F13/INDEX('Taux de change'!$B$5:$B$8,MATCH($D13,'Taux de change'!$A$5:$A$8,0))) | I13: CB / PIX
A14: 14h00–15h30 | B14: Check-in auberge (Vila Madalena, Bela Vista ou Pinheiros) — lit en dortoir | D14: BRL | E14: 70 | F14: 130 | G14: =IF($D14="","",E14/INDEX('Taux de change'!$B$5:$B$8,MATCH($D14,'Taux de change'!$A$5:$A$8,0))) | H14: =IF($D14="","",F14/INDEX('Taux de change'!$B$5:$B$8,MATCH($D14,'Taux de change'!$A$5:$A$8,0))) | I14: CB
A15: 16h00–17h30 | B15: Beco do Batman, Vila Madalena (street art) + métro/bus | D15: BRL | E15: 5.4 | F15: 10.8 | G15: =IF($D15="","",E15/INDEX('Taux de change'!$B$5:$B$8,MATCH($D15,'Taux de change'!$A$5:$A$8,0))) | H15: =IF($D15="","",F15/INDEX('Taux de change'!$B$5:$B$8,MATCH($D15,'Taux de change'!$A$5:$A$8,0))) | I15: CB sans contact
A16: 17h30–19h00 | B16: Centro : Theatro Municipal, Edifício Copan (Niemeyer), Farol Santander (mirador 26ᵉ étage) | D16: BRL | E16: 30 | F16: 40 | G16: =IF($D16="","",E16/INDEX('Taux de change'!$B$5:$B$8,MATCH($D16,'Taux de change'!$A$5:$A$8,0))) | H16: =IF($D16="","",F16/INDEX('Taux de change'!$B$5:$B$8,MATCH($D16,'Taux de change'!$A$5:$A$8,0))) | I16: CB
A17: 19h30–21h00 | B17: Dîner + chope artisanale, Rua Aspicuelta (Vila Madalena) | D17: BRL | E17: 50 | F17: 90 | G17: =IF($D17="","",E17/INDEX('Taux de change'!$B$5:$B$8,MATCH($D17,'Taux de change'!$A$5:$A$8,0))) | H17: =IF($D17="","",F17/INDEX('Taux de change'!$B$5:$B$8,MATCH($D17,'Taux de change'!$A$5:$A$8,0))) | I17: CB / PIX
A19: TOTAL JOUR 13 | G19: =SUM(G6:G17) | H19: =SUM(H6:H17)
A21: Détail par devise
A22: Total R$ (BRL) | E22: =SUMIF($D$6:$D$17,"BRL",E6:E17) | F22: =SUMIF($D$6:$D$17,"BRL",F6:F17)
A24: Colonnes E et F = fourchette basse / haute en monnaie locale. Colonnes G et H = conversion automatique via la feuille « Taux de change ».

Sheet J14 - Sao Paulo 2
A1: JOUR 14 — SÃO PAULO — jour 2
A2: Luz, Mercadão, Ibirapuera, Liberdade — puis bus de nuit
A3: Altitude : 760 m
A5: Horaires | B5: Activité / prestation | C5: Détail, vigilance, alternative | D5: Devise | E5: Coût local min | F5: Coût local max | G5: Coût USD min | H5: Coût USD max | I5: Paiement
A6: 07h30–08h30 | B6: Petit-déjeuner à l'auberge (souvent inclus) | D6: BRL | E6: 0 | F6: 20 | G6: =IF($D6="","",E6/INDEX('Taux de change'!$B$5:$B$8,MATCH($D6,'Taux de change'!$A$5:$A$8,0))) | H6: =IF($D6="","",F6/INDEX('Taux de change'!$B$5:$B$8,MATCH($D6,'Taux de change'!$A$5:$A$8,0))) | I6: CB
A7: 08h30–09h00 | B7: Métro ligne 1 → Luz | D7: BRL | E7: 5.4 | F7: 5.4 | G7: =IF($D7="","",E7/INDEX('Taux de change'!$B$5:$B$8,MATCH($D7,'Taux de change'!$A$5:$A$8,0))) | H7: =IF($D7="","",F7/INDEX('Taux de change'!$B$5:$B$8,MATCH($D7,'Taux de change'!$A$5:$A$8,0))) | I7: CB sans contact
A8: 09h00–10h30 | B8: Pinacoteca do Estado (1ᵉʳ musée d'art du Brésil) + Jardim da Luz | C8: Gratuit le samedi. | D8: BRL | E8: 0 | F8: 50 | G8: =IF($D8="","",E8/INDEX('Taux de change'!$B$5:$B$8,MATCH($D8,'Taux de change'!$A$5:$A$8,0))) | H8: =IF($D8="","",F8/INDEX('Taux de change'!$B$5:$B$8,MATCH($D8,'Taux de change'!$A$5:$A$8,0))) | I8: CB
A9: 10h30–11h30 | B9: Mercado Municipal (Mercadão) : sanduíche de mortadela (300 g de charcuterie) + pastel de bacalhau | C9: Attention aux « dégustations » de fruits imposées par les vendeurs : elles vous seront facturées R$ 30–60. | D9: BRL | E9: 60 | F9: 100 | G9: =IF($D9="","",E9/INDEX('Taux de change'!$B$5:$B$8,MATCH($D9,'Taux de change'!$A$5:$A$8,0))) | H9: =IF($D9="","",F9/INDEX('Taux de change'!$B$5:$B$8,MATCH($D9,'Taux de change'!$A$5:$A$8,0))) | I9: CB / PIX
A10: 11h30–12h30 | B10: Rua 25 de Março + Catedral da Sé + Pátio do Colégio | C10: Zone à surveiller : ne sortez pas votre téléphone dans la rue autour de la Sé et de la Luz. | I10: —
A11: 12h30–13h30 | B11: Métro + bus → Parque Ibirapuera | D11: BRL | E11: 5.4 | F11: 9.4 | G11: =IF($D11="","",E11/INDEX('Taux de change'!$B$5:$B$8,MATCH($D11,'Taux de change'!$A$5:$A$8,0))) | H11: =IF($D11="","",F11/INDEX('Taux de change'!$B$5:$B$8,MATCH($D11,'Taux de change'!$A$5:$A$8,0))) | I11: CB sans contact
A12: 13h30–17h00 | B12: Parc Ibirapuera (gratuit), MAC-USP (gratuit, terrasse panoramique), Museu Afro Brasil | C12: Museu Afro Brasil gratuit le samedi. | D12: BRL | E12: 0 | F12: 45 | G12: =IF($D12="","",E12/INDEX('Taux de change'!$B$5:$B$8,MATCH($D12,'Taux de change'!$A$5:$A$8,0))) | H12: =IF($D12="","",F12/INDEX('Taux de change'!$B$5:$B$8,MATCH($D12,'Taux de change'!$A$5:$A$8,0))) | I12: CB
A13: 17h00–18h30 | B13: Liberdade (quartier japonais) : gyoza, taiyaki, Rua Galvão Bueno | D13: BRL | E13: 25 | F13: 45 | G13: =IF($D13="","",E13/INDEX('Taux de change'!$B$5:$B$8,MATCH($D13,'Taux de change'!$A$5:$A$8,0))) | H13: =IF($D13="","",F13/INDEX('Taux de change'!$B$5:$B$8,MATCH($D13,'Taux de change'!$A$5:$A$8,0))) | I13: CB / PIX
A14: 18h30–20h00 | B14: Récupération des sacs à l'auberge + dîner | D14: BRL | E14: 40 | F14: 70 | G14: =IF($D14="","",E14/INDEX('Taux de change'!$B$5:$B$8,MATCH($D14,'Taux de change'!$A$5:$A$8,0))) | H14: =IF($D14="","",F14/INDEX('Taux de change'!$B$5:$B$8,MATCH($D14,'Taux de change'!$A$5:$A$8,0))) | I14: CB / PIX
A15: 20h30–21h30 | B15: Métro → Terminal Tietê + taxe d'embarquement | D15: BRL | E15: 5.4 | F15: 5.4 | G15: =IF($D15="","",E15/INDEX('Taux de change'!$B$5:$B$8,MATCH($D15,'Taux de change'!$A$5:$A$8,0))) | H15: =IF($D15="","",F15/INDEX('Taux de change'!$B$5:$B$8,MATCH($D15,'Taux de change'!$A$5:$A$8,0))) | I15: CB sans contact
A16: 23h00 | B16: BUS SÃO PAULO → RIO — Viação 1001 / Cometa / Águia Branca · 429 km · 6 h–6 h 45 · executivo ou leito | C16: Conventionnel dès R$ 60–90 (Buser, ClickBus). Le bus de nuit économise une nuit d'auberge et vous dépose à l'aube. | D16: BRL | E16: 100 | F16: 200 | G16: =IF($D16="","",E16/INDEX('Taux de change'!$B$5:$B$8,MATCH($D16,'Taux de change'!$A$5:$A$8,0))) | H16: =IF($D16="","",F16/INDEX('Taux de change'!$B$5:$B$8,MATCH($D16,'Taux de change'!$A$5:$A$8,0))) | I16: CB en ligne
A17: Nuit | B17: Nuit à bord | I17: —
A19: TOTAL JOUR 14 | G19: =SUM(G6:G17) | H19: =SUM(H6:H17)
A21: Détail par devise
A22: Total R$ (BRL) | E22: =SUMIF($D$6:$D$17,"BRL",E6:E17) | F22: =SUMIF($D$6:$D$17,"BRL",F6:F17)
A24: Colonnes E et F = fourchette basse / haute en monnaie locale. Colonnes G et H = conversion automatique via la feuille « Taux de change ».

Sheet J15 - Rio 1
A1: JOUR 15 — RIO DE JANEIRO — jour 1
A2: CHRIST RÉDEMPTEUR, Santa Teresa et Lapa
A3: Altitude : 0–710 m
A5: Horaires | B5: Activité / prestation | C5: Détail, vigilance, alternative | D5: Devise | E5: Coût local min | F5: Coût local max | G5: Coût USD min | H5: Coût USD max | I5: Paiement
A6: 05h15–05h45 | B6: Arrivée Rodoviária do Rio (Novo Rio) | I6: —
A7: 05h45–06h30 | B7: Uber / 99 → Copacabana ou Botafogo (~8 km) | C7: À cette heure, n'allez pas à pied autour de la rodoviária. Uber ou 99 exclusivement, jamais un taxi non officiel. | D7: BRL | E7: 30 | F7: 55 | G7: =IF($D7="","",E7/INDEX('Taux de change'!$B$5:$B$8,MATCH($D7,'Taux de change'!$A$5:$A$8,0))) | H7: =IF($D7="","",F7/INDEX('Taux de change'!$B$5:$B$8,MATCH($D7,'Taux de change'!$A$5:$A$8,0))) | I7: CB (in-app)
A8: 06h30–08h00 | B8: Dépôt des sacs à l'auberge + petit-déjeuner (pão de queijo + suco de açaí) | D8: BRL | E8: 20 | F8: 35 | G8: =IF($D8="","",E8/INDEX('Taux de change'!$B$5:$B$8,MATCH($D8,'Taux de change'!$A$5:$A$8,0))) | H8: =IF($D8="","",F8/INDEX('Taux de change'!$B$5:$B$8,MATCH($D8,'Taux de change'!$A$5:$A$8,0))) | I8: CB / PIX
A9: 08h00–08h30 | B9: Métro ligne 1 → Largo do Machado (point de départ des vans officielles) | C9: Tarif unique métro Rio 2026 : R$ 7,90. | D9: BRL | E9: 7.9 | F9: 7.9 | G9: =IF($D9="","",E9/INDEX('Taux de change'!$B$5:$B$8,MATCH($D9,'Taux de change'!$A$5:$A$8,0))) | H9: =IF($D9="","",F9/INDEX('Taux de change'!$B$5:$B$8,MATCH($D9,'Taux de change'!$A$5:$A$8,0))) | I9: CB sans contact
A10: 08h30–09h00 | B10: BILLET CHRIST RÉDENTEUR — van officielle Paineiras Corcovado depuis Largo do Machado (A/R + entrée du monument) | C10: Alternatives : train du Corcovado depuis Cosme Velho R$ 134 (le plus pittoresque, 20 min dans la forêt de Tijuca) ; van depuis le centre de visiteurs de Paineiras R$ 87 (le moins cher, mais il faut monter jusqu'à Paineiras). Réservez la veille sur paineirascorcovado.com.br ou ticket.corcovado.com.br : les créneaux du matin partent vite. | D10: BRL | E10: 132 | F10: 132 | G10: =IF($D10="","",E10/INDEX('Taux de change'!$B$5:$B$8,MATCH($D10,'Taux de change'!$A$5:$A$8,0))) | H10: =IF($D10="","",F10/INDEX('Taux de change'!$B$5:$B$8,MATCH($D10,'Taux de change'!$A$5:$A$8,0))) | I10: CB en ligne
A11: 09h00–12h00 | B11: CHRIST RÉDEMPTEUR (710 m) — montée, 1 h sur l'esplanade, redescente | C11: Venez le plus tôt possible : dès 10h30 la plateforme est saturée et les nuages montent souvent l'après-midi. | I11: —
A12: 12h30–13h30 | B12: Almoço por quilo à Largo do Machado / Catete | D12: BRL | E12: 40 | F12: 60 | G12: =IF($D12="","",E12/INDEX('Taux de change'!$B$5:$B$8,MATCH($D12,'Taux de change'!$A$5:$A$8,0))) | H12: =IF($D12="","",F12/INDEX('Taux de change'!$B$5:$B$8,MATCH($D12,'Taux de change'!$A$5:$A$8,0))) | I12: CB / PIX
A13: 14h00–15h00 | B13: Check-in auberge (Copacabana, Botafogo ou Santa Teresa) — lit en dortoir | D13: BRL | E13: 75 | F13: 140 | G13: =IF($D13="","",E13/INDEX('Taux de change'!$B$5:$B$8,MATCH($D13,'Taux de change'!$A$5:$A$8,0))) | H13: =IF($D13="","",F13/INDEX('Taux de change'!$B$5:$B$8,MATCH($D13,'Taux de change'!$A$5:$A$8,0))) | I13: CB
A14: 15h30–17h00 | B14: Escadaria Selarón (gratuit) + Arcos da Lapa + Catedral Metropolitana | D14: BRL | E14: 5 | F14: 10 | G14: =IF($D14="","",E14/INDEX('Taux de change'!$B$5:$B$8,MATCH($D14,'Taux de change'!$A$5:$A$8,0))) | H14: =IF($D14="","",F14/INDEX('Taux de change'!$B$5:$B$8,MATCH($D14,'Taux de change'!$A$5:$A$8,0))) | I14: Espèces / PIX
A15: 17h00–18h30 | B15: Bonde de Santa Teresa (tramway historique) aller-retour + Largo dos Guimarães | D15: BRL | E15: 20 | F15: 20 | G15: =IF($D15="","",E15/INDEX('Taux de change'!$B$5:$B$8,MATCH($D15,'Taux de change'!$A$5:$A$8,0))) | H15: =IF($D15="","",F15/INDEX('Taux de change'!$B$5:$B$8,MATCH($D15,'Taux de change'!$A$5:$A$8,0))) | I15: CB / Riocard
A16: 19h30–21h00 | B16: Dîner à Lapa : feijoada ou picanha + caipirinha, avec samba live | C16: Le « couvert artístico » (R$ 15–30) s'ajoute souvent, plus 10 % de service : vérifiez l'addition. | D16: BRL | E16: 55 | F16: 95 | G16: =IF($D16="","",E16/INDEX('Taux de change'!$B$5:$B$8,MATCH($D16,'Taux de change'!$A$5:$A$8,0))) | H16: =IF($D16="","",F16/INDEX('Taux de change'!$B$5:$B$8,MATCH($D16,'Taux de change'!$A$5:$A$8,0))) | I16: CB / PIX
A18: TOTAL JOUR 15 | G18: =SUM(G6:G16) | H18: =SUM(H6:H16)
A20: Détail par devise
A21: Total R$ (BRL) | E21: =SUMIF($D$6:$D$16,"BRL",E6:E16) | F21: =SUMIF($D$6:$D$16,"BRL",F6:F16)
A23: Colonnes E et F = fourchette basse / haute en monnaie locale. Colonnes G et H = conversion automatique via la feuille « Taux de change ».

Sheet J16 - Rio 2
A1: JOUR 16 — RIO DE JANEIRO — jour 2
A2: Pain de Sucre, Copacabana et Ipanema
A3: Altitude : 0–396 m
A5: Horaires | B5: Activité / prestation | C5: Détail, vigilance, alternative | D5: Devise | E5: Coût local min | F5: Coût local max | G5: Coût USD min | H5: Coût USD max | I5: Paiement
A6: 07h30–08h30 | B6: Petit-déjeuner | D6: BRL | E6: 15 | F6: 30 | G6: =IF($D6="","",E6/INDEX('Taux de change'!$B$5:$B$8,MATCH($D6,'Taux de change'!$A$5:$A$8,0))) | H6: =IF($D6="","",F6/INDEX('Taux de change'!$B$5:$B$8,MATCH($D6,'Taux de change'!$A$5:$A$8,0))) | I6: CB / PIX
A7: 08h30–09h00 | B7: Bus ou métro + marche → Praia Vermelha (Urca) | D7: BRL | E7: 4.7 | F7: 7.9 | G7: =IF($D7="","",E7/INDEX('Taux de change'!$B$5:$B$8,MATCH($D7,'Taux de change'!$A$5:$A$8,0))) | H7: =IF($D7="","",F7/INDEX('Taux de change'!$B$5:$B$8,MATCH($D7,'Taux de change'!$A$5:$A$8,0))) | I7: CB sans contact
A8: 09h00–12h00 | B8: BONDINHO DO PÃO DE AÇÚCAR — 2 téléphériques : Praia Vermelha → Morro da Urca (220 m) → Pain de Sucre (396 m) | C8: R$ 205 tarif général / R$ 160 pour les résidents au Brésil. Achetez en ligne sur bondinho.com.br : la file de la billetterie dépasse souvent 1 h. Le « Acesso Rápido » coupe-file est à R$ 325 — inutile si vous venez à 09h00. | D8: BRL | E8: 160 | F8: 205 | G8: =IF($D8="","",E8/INDEX('Taux de change'!$B$5:$B$8,MATCH($D8,'Taux de change'!$A$5:$A$8,0))) | H8: =IF($D8="","",F8/INDEX('Taux de change'!$B$5:$B$8,MATCH($D8,'Taux de change'!$A$5:$A$8,0))) | I8: CB en ligne
A9: 12h00–13h00 | B9: Pista Cláudio Coutinho (sentier côtier gratuit au pied du Pain de Sucre, ouistitis) | I9: —
A10: 13h00–14h00 | B10: Almoço à Urca ou Botafogo | D10: BRL | E10: 40 | F10: 65 | G10: =IF($D10="","",E10/INDEX('Taux de change'!$B$5:$B$8,MATCH($D10,'Taux de change'!$A$5:$A$8,0))) | H10: =IF($D10="","",F10/INDEX('Taux de change'!$B$5:$B$8,MATCH($D10,'Taux de change'!$A$5:$A$8,0))) | I10: CB / PIX
A11: 14h30–17h00 | B11: Plage de Copacabana : location chaise + parasol, água de coco, biscoito Globo, açaí | C11: Les vendeurs de plage acceptent presque tous le PIX ; sinon petites coupures. N'emportez sur le sable que le strict minimum. | D11: BRL | E11: 55 | F11: 90 | G11: =IF($D11="","",E11/INDEX('Taux de change'!$B$5:$B$8,MATCH($D11,'Taux de change'!$A$5:$A$8,0))) | H11: =IF($D11="","",F11/INDEX('Taux de change'!$B$5:$B$8,MATCH($D11,'Taux de change'!$A$5:$A$8,0))) | I11: Espèces / PIX
A12: 17h00–18h30 | B12: Ipanema puis coucher de soleil sur la Pedra do Arpoador (gratuit, applaudissements au dernier rayon) | I12: —
A13: 18h30–19h30 | B13: Rua Farme de Amoedo / Feira Hippie de Ipanema (le dimanche) | I13: —
A14: 20h00–21h30 | B14: Dîner à Ipanema : moqueca ou bar à petiscos | D14: BRL | E14: 60 | F14: 110 | G14: =IF($D14="","",E14/INDEX('Taux de change'!$B$5:$B$8,MATCH($D14,'Taux de change'!$A$5:$A$8,0))) | H14: =IF($D14="","",F14/INDEX('Taux de change'!$B$5:$B$8,MATCH($D14,'Taux de change'!$A$5:$A$8,0))) | I14: CB / PIX
A15: Nuit | B15: Auberge Rio (2ᵉ nuit) | D15: BRL | E15: 75 | F15: 140 | G15: =IF($D15="","",E15/INDEX('Taux de change'!$B$5:$B$8,MATCH($D15,'Taux de change'!$A$5:$A$8,0))) | H15: =IF($D15="","",F15/INDEX('Taux de change'!$B$5:$B$8,MATCH($D15,'Taux de change'!$A$5:$A$8,0))) | I15: CB
A17: TOTAL JOUR 16 | G17: =SUM(G6:G15) | H17: =SUM(H6:H15)
A19: Détail par devise
A20: Total R$ (BRL) | E20: =SUMIF($D$6:$D$15,"BRL",E6:E15) | F20: =SUMIF($D$6:$D$15,"BRL",F6:F15)
A22: Colonnes E et F = fourchette basse / haute en monnaie locale. Colonnes G et H = conversion automatique via la feuille « Taux de change ».

Sheet J17 - Rio 3
A1: JOUR 17 — RIO DE JANEIRO — jour 3
A2: Jardin botanique, Parque Lage, Maracanã et Porto Maravilha
A3: Altitude : 0–60 m
A5: Horaires | B5: Activité / prestation | C5: Détail, vigilance, alternative | D5: Devise | E5: Coût local min | F5: Coût local max | G5: Coût USD min | H5: Coût USD max | I5: Paiement
A6: 07h30–08h30 | B6: Petit-déjeuner | D6: BRL | E6: 15 | F6: 30 | G6: =IF($D6="","",E6/INDEX('Taux de change'!$B$5:$B$8,MATCH($D6,'Taux de change'!$A$5:$A$8,0))) | H6: =IF($D6="","",F6/INDEX('Taux de change'!$B$5:$B$8,MATCH($D6,'Taux de change'!$A$5:$A$8,0))) | I6: CB / PIX
A7: 08h30–09h15 | B7: Métro + bus ou Uber → Jardim Botânico | D7: BRL | E7: 8 | F7: 35 | G7: =IF($D7="","",E7/INDEX('Taux de change'!$B$5:$B$8,MATCH($D7,'Taux de change'!$A$5:$A$8,0))) | H7: =IF($D7="","",F7/INDEX('Taux de change'!$B$5:$B$8,MATCH($D7,'Taux de change'!$A$5:$A$8,0))) | I7: CB
A8: 09h15–11h30 | B8: JARDIN BOTANIQUE DE RIO (1808) : allée des palmiers impériaux, orchidarium, victorias regias — tarif visiteur étranger | C8: R$ 80 pour les étrangers non résidents, R$ 40 pour les résidents au Brésil. Billet sur jbrj.eleventickets.com. | D8: BRL | E8: 80 | F8: 80 | G8: =IF($D8="","",E8/INDEX('Taux de change'!$B$5:$B$8,MATCH($D8,'Taux de change'!$A$5:$A$8,0))) | H8: =IF($D8="","",F8/INDEX('Taux de change'!$B$5:$B$8,MATCH($D8,'Taux de change'!$A$5:$A$8,0))) | I8: CB en ligne
A9: 11h30–13h00 | B9: Parque Lage (gratuit) : palais, piscine et vue sur le Christ + café dans la cour | D9: BRL | E9: 25 | F9: 45 | G9: =IF($D9="","",E9/INDEX('Taux de change'!$B$5:$B$8,MATCH($D9,'Taux de change'!$A$5:$A$8,0))) | H9: =IF($D9="","",F9/INDEX('Taux de change'!$B$5:$B$8,MATCH($D9,'Taux de change'!$A$5:$A$8,0))) | I9: CB / PIX
A10: 13h00–14h00 | B10: Almoço à Botafogo | D10: BRL | E10: 40 | F10: 60 | G10: =IF($D10="","",E10/INDEX('Taux de change'!$B$5:$B$8,MATCH($D10,'Taux de change'!$A$5:$A$8,0))) | H10: =IF($D10="","",F10/INDEX('Taux de change'!$B$5:$B$8,MATCH($D10,'Taux de change'!$A$5:$A$8,0))) | I10: CB / PIX
A11: 14h30–16h30 | B11: MARACANÃ — tour guidé du stade (vestiaires, tunnel, pelouse, salle des trophées) | C11: R$ 94 plein tarif sur tourmaracana.com.br. Si un match Flamengo/Fluminense/Vasco tombe pendant votre séjour, le billet de tribune (R$ 60–150) vaut largement mieux que le tour. | D11: BRL | E11: 94 | F11: 94 | G11: =IF($D11="","",E11/INDEX('Taux de change'!$B$5:$B$8,MATCH($D11,'Taux de change'!$A$5:$A$8,0))) | H11: =IF($D11="","",F11/INDEX('Taux de change'!$B$5:$B$8,MATCH($D11,'Taux de change'!$A$5:$A$8,0))) | I11: CB en ligne
A12: 17h00–19h00 | B12: Boulevard Olímpico : fresque « Etnias » de Kobra, AquaRio, Museu do Amanhã (Calatrava) | C12: Museu do Amanhã R$ 30–40 ; gratuit le mardi. Zone animée le week-end (roda de samba de la Pedra do Sal le lundi soir). | D12: BRL | E12: 0 | F12: 40 | G12: =IF($D12="","",E12/INDEX('Taux de change'!$B$5:$B$8,MATCH($D12,'Taux de change'!$A$5:$A$8,0))) | H12: =IF($D12="","",F12/INDEX('Taux de change'!$B$5:$B$8,MATCH($D12,'Taux de change'!$A$5:$A$8,0))) | I12: CB
A13: 19h30–21h30 | B13: Dîner d'adieu : churrascaria rodízio ou botequim de Botafogo | D13: BRL | E13: 80 | F13: 160 | G13: =IF($D13="","",E13/INDEX('Taux de change'!$B$5:$B$8,MATCH($D13,'Taux de change'!$A$5:$A$8,0))) | H13: =IF($D13="","",F13/INDEX('Taux de change'!$B$5:$B$8,MATCH($D13,'Taux de change'!$A$5:$A$8,0))) | I13: CB / PIX
A14: Nuit | B14: Auberge Rio (3ᵉ nuit) | D14: BRL | E14: 75 | F14: 140 | G14: =IF($D14="","",E14/INDEX('Taux de change'!$B$5:$B$8,MATCH($D14,'Taux de change'!$A$5:$A$8,0))) | H14: =IF($D14="","",F14/INDEX('Taux de change'!$B$5:$B$8,MATCH($D14,'Taux de change'!$A$5:$A$8,0))) | I14: CB
A16: TOTAL JOUR 17 | G16: =SUM(G6:G14) | H16: =SUM(H6:H14)
A18: Détail par devise
A19: Total R$ (BRL) | E19: =SUMIF($D$6:$D$14,"BRL",E6:E14) | F19: =SUMIF($D$6:$D$14,"BRL",F6:F14)
A21: Colonnes E et F = fourchette basse / haute en monnaie locale. Colonnes G et H = conversion automatique via la feuille « Taux de change ».

Sheet Paiements par pays
A1: Paiements par pays
A2: Où la carte passe, où il faut du liquide, et comment retirer sans se faire piéger.
A5: Pays | B5: Carte bancaire | C5: Espèces | D5: Distributeurs et change
A6: PÉROUSol (S/) | B6: Acceptée dans les hôtels, restaurants et supermarchés de Lima et Puno. Visa passe partout, Mastercard moins. Les billets de bus Civa et Cruz del Sur s'achètent en ligne par carte. | C6: Indispensable pour : mototaxis, menús, marchés, entrées de sites, taxe de terminal. Le paiement local se fait surtout par Yape / Plin (QR), inaccessible sans compte bancaire péruvien. | D6: BCP, Interbank, Scotiabank : frais de S/ 18–25 par retrait. Banco de la Nación est le moins cher. Refusez toujours la « conversion en euros » proposée par le DAB (DCC).
A7: BOLIVIEBoliviano (Bs) | B7: Le maillon faible du voyage. Carte acceptée seulement dans certains hôtels et restaurants de La Paz et Santa Cruz, souvent avec +5 % de majoration. À Copacabana, sur l'Isla del Sol, dans les bus et aux frontières : aucune carte. | C7: Tout se paie en espèces. Les Boliviens paient par QR bancaire (SIMPLE, BCP), impossible sans compte local. Gardez des petites coupures : personne ne rend sur un billet de Bs 200 (barge de Tiquina, tickets communautaires, micros). | D7: DAB souvent vides ou plafonnés à Bs 700–2 000 par retrait, avec Bs 25–35 de frais locaux. Solution : arriver avec des dollars US en billets neufs et les changer en casa de cambio. Un billet froissé, annoté ou légèrement déchiré est refusé. Taux officiel BCB Bs 12,04/$ ; marché parallèle Bs ~11,75/$ — l'écart s'est refermé depuis la dévaluation de décembre 2025, le change en casa de cambio est donc redevenu correct.
A8: PARAGUAYGuaraní (Gs) | B8: Largement acceptée à Asunción : restaurants, centres commerciaux, supermarchés, Bolt et Uber. Le billet international de bus s'achète par carte au guichet du terminal. | C8: Nécessaire au Mercado 4, dans les bus interurbains, à Areguá et pour les pourboires. Les bus urbains d'Asunción n'acceptent plus les espèces : carte « Billetaje Electrónico » rechargeable (Gs 10 000). | D8: DAB Itaú, Continental, Ueno : frais de Gs 25 000–35 000. Certains DAB distribuent aussi des dollars. Ne gardez aucun guaraní en sortant : c'est une monnaie inéchangeable hors du Paraguay.
A9: BRÉSILReal (R$) | B9: Le pays le plus facile du continent. Sans contact accepté partout, y compris aux tourniquets du métro de São Paulo et de Rio, chez les vendeurs de plage et dans les bus longue distance. | C9: Presque inutile. Le PIX (virement instantané par QR) est le standard national, mais il demande un CPF brésilien. Gardez R$ 100–150 en petites coupures pour les plages, le bonde et les dons. | D9: Banco24Horas, Bradesco, Banco do Brasil : R$ 20–25 par retrait, plafond R$ 1 000–1 500. Évitez les DAB de l'aéroport et de la rodoviária. Le taux affiché par une carte type Revolut/Wise est meilleur que toutes les casas de câmbio.

Sheet Frontieres
A1: Frontieres
A2: Trois passages terrestres. Aucun ne coûte un centime officiellement — mais l'un d'eux peut vous refouler.
A5: Passage | B5: Où et quand | C5: Formalités | D5: Frais officiels
A6: Pérou → BolivieYunguyo / Kasani | B6: J3, ~09h30–11h00Compter 45 min à 1 h 30 | C6: Descente du bus, tampon de sortie côté péruvien (Migraciones Yunguyo), 300 m à pied, puis tampon d'entrée côté bolivien (Migración Kasani). Pas de visa pour un passeport français, séjour de 90 jours — demandez-le explicitement, certains agents tamponnent 30 jours par défaut. | D6: 0Si on vous réclame une « boleta » de Bs 10–20 ou un « impuesto municipal », demandez un reçu officiel : cette taxe n'existe pas.
A7: Bolivie → ParaguayIbibobo → Infante Rivarola → Mariscal Estigarribia | B7: J9, ~07h00–12h00Compter 3 à 5 h au total | C7: Le passage le plus long et le plus strict du voyage. Tampon de sortie bolivien, 100 km de no man's land, puis au Paraguay : migration + contrôle sanitaire du carnet de vaccination contre la fièvre jaune + fouille douanière complète des sacs (contrebande). Le certificat est obligatoire de 1 à 59 ans pour tout voyageur venant des départements de Santa Cruz ou du Beni, et la vaccination doit dater de plus de 10 jours. Pas de visa pour les Français, 90 jours. | D7: 0Aucune taxe officielle d'entrée ni de sortie. Prévoyez malgré tout Bs 20–40 en petites coupures pour les WC et l'eau aux postes.
A8: Paraguay → BrésilCiudad del Este / Foz do Iguaçu (Puente de la Amistad) | B8: J12, ~12h30–14h30Compter 1 h 30 à 2 h | C8: Le piège classique du voyageur. Beaucoup de bus ne marquent l'arrêt que du côté brésilien : il faut descendre avec tous ses bagages et exiger les deux tampons. Sans tampon de sortie paraguayen, vous serez considéré comme ayant dépassé votre séjour et sanctionné lors d'un contrôle ultérieur. Pas de visa pour les Français, 90 jours. | D8: 0Le Brésil n'exige pas de certificat de fièvre jaune à l'entrée, mais il reste vivement recommandé (et vous l'aurez déjà pour le Paraguay).

Sheet Hors planning
A1: Coûts hors planning quotidien
A2: À prévoir avant le départ ou en réserve. Montants en euros, payés depuis la France.
A5: Poste | B5: Min € | C5: Max € | D5: Paiement | E5: Détail
A6: Vaccin fièvre jaune (Stamaril) + carnet international | B6: 60 | C6: 90 | D6: CB | E6: OBLIGATOIRE pour entrer au Paraguay depuis Santa Cruz. À faire au moins 10 jours avant le passage de frontière, en centre de vaccinations internationales.
A7: Assurance voyage / rapatriement 3 semaines (Chapka, Heymondo, ACS) | B7: 45 | C7: 90 | D7: CB | E7: Indispensable : la Route de la Mort et l'altitude sont souvent exclues des assurances de carte bancaire.
A8: Consultation santé voyage + traitement altitude (acétazolamide) | B8: 25 | C8: 50 | D8: CB
A9: eSIM multi-pays Amérique du Sud 20 Go (Airalo, Holafly) — alternative aux 4 SIM locales | B9: 35 | C9: 55 | D9: CB | E9: Sinon : Claro PE S/ 30, Entel BO Bs 50, Tigo PY Gs 50 000, Vivo BR R$ 40 ≈ $35 au total.
A10: Lessive : 4 lavages au kilo sur le trajet | B10: 18 | C10: 30 | D10: Espèces | E10: Pérou S/ 8–12/kg · Bolivie Bs 12–18/kg · Paraguay Gs 20 000/kg · Brésil R$ 20–28/kg.
A11: Frais bancaires : 6–8 retraits DAB + commissions de change | B11: 45 | C11: 90 | D11: — | E11: Prenez une carte sans frais (Revolut, N26, Wise). Les DAB boliviens facturent Bs 25–35 par retrait EN PLUS de votre banque.
A12: Réserve « imprévus » : grève de bus, bus annulé au Chaco, nuit d'hôtel forcée, pharmacie | B12: 150 | C12: 250 | D12: — | E12: Le tronçon Santa Cruz → Asunción n'a qu'un départ par jour, 5 jours sur 7 : une annulation coûte une nuit + un jour.
A13: Coussin de cash en dollars US — billets neufs, non pliés, non annotés | B13: 300 | C13: 400 | D13: Espèces | E13: Pour la Bolivie surtout : DAB régulièrement vides et plafonnés. Les casas de cambio refusent tout billet marqué ou déchiré.
A15: TOTAL HORS PLANNING | B15: =SUM(B6:B13) | C15: =SUM(C6:C13) | E15: Dont 300–400 € de réserve en cash qui seront dépensés sur place, donc déjà comptés dans les totaux journaliers.

Sheet A savoir
A1: Ce qu'il faut savoir avant de valider ce planning
A2: Points de fragilité, budget moyen par pays, économies possibles et fiabilité des prix.
A4: LES 4 POINTS DE FRAGILITÉ
A5: • | B5: Bus Santa Cruz → Asunción : un seul départ par jour, 5 jours sur 7 (lun, mar, mer, ven, sam à 19h00). Si le J8 tombe un jeudi ou un dimanche, vous perdez 24 h.
A6: • | B6: Nord de l'Isla del Sol (Roca Sagrada, Chincana) : fermé par intermittence depuis 2017 pour conflit entre communautés. Demandez au guichet du quai AVANT d'acheter le bateau.
A7: • | B7: Blocages routiers boliviens (bloqueos) : fréquents, ils coupent l'axe La Paz – Santa Cruz sans préavis. Gardez une journée tampon.
A8: • | B8: Altitude : Lima 154 m → Puno 3 827 m en une nuit de bus. C'est le vrai risque du voyage, bien avant la Route de la Mort. Demi-journée de repos au J2, sans négociation.
A10: OBLIGATOIRE AVANT LE DÉPART
A11: • | B11: Vaccin contre la fièvre jaune (Stamaril) + carnet international de vaccination, au moins 10 jours avant le passage Bolivie → Paraguay.
A12: • | B12: Le Paraguay l'exige (Résolution 268/2025) pour tout voyageur de 1 à 59 ans venant d'une zone à risque. Le département de Santa Cruz, d'où part votre bus, en fait partie.
A13: • | B13: Sans carnet valide, vous êtes refoulé au poste de Mariscal Estigarribia, en plein Chaco, à 700 km d'Asunción.
A14: • | B14: Dollars US en billets neufs, non pliés, non annotés, pour la Bolivie : les casas de cambio refusent tout billet marqué ou déchiré.
A16: COÛT D'UNE JOURNÉE MOYENNE
A17: • | B17: Pérou : environ 45 $/jour (auberge 12 $, repas 12 $, transports 8 $, visites 8 $).
A18: • | B18: Bolivie : environ 35 $/jour hors Route de la Mort — le pays le moins cher du parcours.
A19: • | B19: Paraguay : environ 50 $/jour — plus cher que la Bolivie, moins que le Brésil.
A20: • | B20: Brésil : environ 85 $/jour. Les entrées pèsent lourd (Christ 26 $, Pain de Sucre 40 $, Jardin botanique 16 $, Maracanã 18 $) et le tarif « étranger non résident » est systématiquement le double du tarif brésilien.
A21: • | B21: Les 7 grands trajets en bus (204–304 $ au total) s'ajoutent à ces moyennes.
A23: OÙ ÉCONOMISER VRAIMENT
A24: • | B24: −85 $ : remplacer la Route de la Mort en VTT par le Valle de la Luna + Valle de las Ánimas.
A25: • | B25: −45 $ : acheter le billet Santa Cruz → Asunción au guichet du terminal plutôt qu'en ligne.
A26: • | B26: −30 $ : bus publics boliviens plutôt que bus touristiques porte-à-porte.
A27: • | B27: −25 $ : viser le mardi pour le MASP, le samedi pour la Pinacoteca et le Museu Afro Brasil, le vendredi ou samedi pour le Museo del Barro — gratuits ces jours-là.
A28: • | B28: −20 $ : monter au Christ par la van depuis Paineiras (R$ 87) au lieu de Largo do Machado (R$ 132).
A29: • | B29: 5 nuits déjà économisées par les bus de nuit (J1, J7, J8, J12, J14), soit environ 70 $ de logement en moins.
A31: FIABILITÉ DES PRIX
A32: • | B32: Vérifiés en ligne le 11/09/2026 : les 4 taux de change, le tarif ATT officiel La Paz → Santa Cruz (Bs 232–319), les billets du Christ Rédempteur (R$ 87 / 132 / 134), du Pain de Sucre (R$ 160 / 205), du Jardin botanique (R$ 80 étranger), du Maracanã (R$ 94), du MASP (R$ 80 / 100), les métros de São Paulo (R$ 5,40) et de Rio (R$ 7,90), le Museo del Barro (Gs 50 000), les bateaux et tickets communautaires de l'Isla del Sol, les horaires et durées des 7 bus, et la règle paraguayenne sur la fièvre jaune.
A33: • | B33: Fourchettes de marché, à confirmer sur place : auberges, repas, taxis et courses Bolt/Uber, prix des bus internationaux au guichet (20 à 40 % d'écart selon la compagnie, la classe et la saison), et le tour de la Route de la Mort.
A34: • | B34: À réserver à l'avance : Lima → Puno (3 à 7 jours), Santa Cruz → Asunción (dès votre arrivée à Santa Cruz), Christ Rédempteur et Pain de Sucre (la veille), auberge de Rio (les week-ends partent vite).
A36: DÉCALAGES HORAIRES
A37: • | B37: Pérou UTC−5 → Bolivie UTC−4 : +1 h au J3 (frontière de Kasani).
A38: • | B38: Bolivie UTC−4 → Paraguay UTC−3 : +1 h au J9 (frontière du Chaco).
A39: • | B39: Paraguay UTC−3 → Brésil / São Paulo UTC−3 : aucun changement au J12.
A40: • | B40: Vous perdez 2 h au total. Les horaires de bus sont toujours donnés en heure locale de départ.
