Workbook

Sheet Synthèse
A1: Planning Lima → La Paz → Asunción → Rio (8 jours, vols)
A2: Résumé budgétaire et hébergement
A4: Catégorie | B4: Estimation basse | C4: Estimation haute | D4: Devise
A5: Hébergement (8 nuits dortoir) | B5: 280 | C5: 440 | D5: USD
A6: Repas (3×jour) | B6: 300 | C6: 480 | D6: USD
A7: Transports locaux | B7: 80 | C7: 140 | D7: USD
A8: Activités et visites | B8: 200 | C8: 320 | D8: USD
A9: Vols (3 directs) | B9: 450 | C9: 700 | D9: USD
A10: TOTAL ON-SITE | B10: 1310 | C10: 2080 | D10: USD
A12: À ajouter:
A13: Assurance voyage | B13: 60 | C13: 100 | D13: USD
A14: Vaccin fièvre jaune | B14: 60 | C14: 80 | D14: USD
A15: Frais bancaires | B15: 30 | C15: 50 | D15: USD
A16: Réserve urgence | B16: 150 | C16: 250 | D16: USD

Sheet Taux de change
A1: Taux de change — cellules d'entrée
A2: Relevés le 11/09/2026. Modifiez la colonne B : tout le classeur se recalcule.
A4: Devise | B4: Unités pour 1 USD | C4: Pays | D4: Remarque
A5: PEN | B5: 3.363 | C5: Pérou (sol, S/) | D5: Taux de marché. Retrait au DAB : frais locaux S/ 18–25 en plus.
A6: BOB | B6: 12.04 | C6: Bolivie (boliviano, Bs) | D6: Taux officiel BCB. Marché parallèle ≈ Bs 11,75 : écart resserré depuis dévaluation déc. 2025.
A7: PYG | B7: 5921.57 | C7: Paraguay (guaraní, Gs) | D7: Monnaie inéchangeable hors Paraguay : ne rien garder en sortant.
A8: BRL | B8: 5.115 | C8: Brésil (real, R$) | D8: Carte Revolut/Wise donne meilleur taux que casas de cambio.
A11: Légende : bleu = valeur saisie à la main (modifiable). Tout le reste = calculé par formule.

Sheet Vols
A1: Vols — tarifs et compagnies
A2: 3 vols directs, réserver 5–14 jours à l'avance
A4: Vol # | B4: Route | C4: Distance | D4: Durée | E4: Compagnies | F4: Tarif local | G4: USD | H4: Notes
A5: 1 | B5: Lima → La Paz | C5: 1 300 km | D5: 1 h 15 | E5: Latam, JETSMART, Viva Air | F5: S/ 180–350 | G5: $54–$104 | H5: Vol direct. Réserver 5–14 jours à l'avance sur skyscanner.com.pe ou latam.com. Petit-déjeuner inclus selon classe.
A6: 2 | B6: La Paz → Asunción | C6: 1 600 km | D6: 2 h 15 | E6: Latam, Viva Air | F6: Bs 200–400 | G6: $17–$33 | H6: Vol direct. Boisson incluse. Réserver 5–14 jours. Décalage horaire −1 h (Bolivie → Paraguay).
A7: 3 | B7: Asunción → Rio | C7: 1 500 km | D7: 2 h 45 | E7: Latam, Azul, Gol | F7: Gs 300 000–550 000 | G7: $51–$93 | H7: Vol direct. Boisson + snack inclus. Réserver 5–14 jours. Décalage +1 h (Paraguay → Brésil).

Sheet J01 - Lima
A1: JOUR 1 — LIMA (Pérou)
A2: Lima — centre historique puis départ pour La Paz
A3: Altitude : 154 m
A5: Horaires | B5: Activité / prestation | C5: Détail, vigilance, alternative | D5: Devise | E5: Coût local min | F5: Coût local max | G5: Coût USD min | H5: Coût USD max | I5: Paiement
A6: 07h30–08h15 | B6: Petit-déjeuner : café + pan con chicharrón / jugo surtido (Miraflores) | D6: PEN | E6: 8 | F6: 15 | G6: =IF(D6="","",E6/INDEX('Taux de change'!$B$5:$B$8,MATCH(D6,'Taux de change'!$A$5:$A$8,0))) | H6: =IF(D6="","",F6/INDEX('Taux de change'!$B$5:$B$8,MATCH(D6,'Taux de change'!$A$5:$A$8,0))) | I6: Espèces
A7: 08h30–09h00 | B7: Metropolitano Miraflores → Centre (station Jr. de la Unión) + achat de la carte rechargeable | C7: Carte S/ 5,40 à l'achat + S/ 3,80 le trajet. Pas de CB aux guichets. | D7: PEN | E7: 6 | F7: 10 | G7: =IF(D7="","",E7/INDEX('Taux de change'!$B$5:$B$8,MATCH(D7,'Taux de change'!$A$5:$A$8,0))) | H7: =IF(D7="","",F7/INDEX('Taux de change'!$B$5:$B$8,MATCH(D7,'Taux de change'!$A$5:$A$8,0))) | I7: Espèces
A8: 09h00–10h00 | B8: Plaza Mayor + Cathédrale de Lima (nef, crypte, musée d'art religieux) | D8: PEN | E8: 30 | F8: 30 | G8: =IF(D8="","",E8/INDEX('Taux de change'!$B$5:$B$8,MATCH(D8,'Taux de change'!$A$5:$A$8,0))) | H8: =IF(D8="","",F8/INDEX('Taux de change'!$B$5:$B$8,MATCH(D8,'Taux de change'!$A$5:$A$8,0))) | I8: CB / esp.
A9: 10h00–11h30 | B9: Couvent San Francisco + catacombes (visite guidée obligatoire, 45 min) | D9: PEN | E9: 20 | F9: 25 | G9: =IF(D9="","",E9/INDEX('Taux de change'!$B$5:$B$8,MATCH(D9,'Taux de change'!$A$5:$A$8,0))) | H9: =IF(D9="","",F9/INDEX('Taux de change'!$B$5:$B$8,MATCH(D9,'Taux de change'!$A$5:$A$8,0))) | I9: CB / esp.
A10: 11h30–12h30 | B10: Jr. de la Unión, Plaza San Martín, Casa de Aliaga (extérieur), Mercado Central | I10: —
A11: 12h30–13h30 | B11: Almuerzo « menú del día » : entrée + plat + boisson (hors zone touristique) | D11: PEN | E11: 15 | F11: 25 | G11: =IF(D11="","",E11/INDEX('Taux de change'!$B$5:$B$8,MATCH(D11,'Taux de change'!$A$5:$A$8,0))) | H11: =IF(D11="","",F11/INDEX('Taux de change'!$B$5:$B$8,MATCH(D11,'Taux de change'!$A$5:$A$8,0))) | I11: Espèces
A12: 13h30–14h30 | B12: Uber / Cabify Centre → Aéroport Jorge Chávez (45 km) | C12: Ne pas héler un taxi dans la rue à Lima. Uber, Cabify ou InDriver uniquement. | D12: PEN | E12: 45 | F12: 70 | G12: =IF(D12="","",E12/INDEX('Taux de change'!$B$5:$B$8,MATCH(D12,'Taux de change'!$A$5:$A$8,0))) | H12: =IF(D12="","",F12/INDEX('Taux de change'!$B$5:$B$8,MATCH(D12,'Taux de change'!$A$5:$A$8,0))) | I12: CB (in-app)
A13: 14h30–15h30 | B13: Enregistrement des bagages + tasa de embarque + passage à la sécurité | D13: PEN | E13: 5 | F13: 5 | G13: =IF(D13="","",E13/INDEX('Taux de change'!$B$5:$B$8,MATCH(D13,'Taux de change'!$A$5:$A$8,0))) | H13: =IF(D13="","",F13/INDEX('Taux de change'!$B$5:$B$8,MATCH(D13,'Taux de change'!$A$5:$A$8,0))) | I13: Espèces
A14: 15h30–16h00 | B14: Repas / boissons / derniers achats en zone d'embarquement | D14: PEN | E14: 25 | F14: 45 | G14: =IF(D14="","",E14/INDEX('Taux de change'!$B$5:$B$8,MATCH(D14,'Taux de change'!$A$5:$A$8,0))) | H14: =IF(D14="","",F14/INDEX('Taux de change'!$B$5:$B$8,MATCH(D14,'Taux de change'!$A$5:$A$8,0))) | I14: CB / esp.
A15: 16h00 | B15: VOL LIMA → LA PAZ — Latam, JETSMART, Viva Air · vol direct · 1 h 15 min · petit déjeuner inclus | C15: Réserver sur skyscanner.com.pe, kayak.com.pe ou directement sur latam.com. Départ 16h00 en général, arrivée 17h45 (−1 h Bolivie). | D15: PEN | E15: 180 | F15: 350 | G15: =IF(D15="","",E15/INDEX('Taux de change'!$B$5:$B$8,MATCH(D15,'Taux de change'!$A$5:$A$8,0))) | H15: =IF(D15="","",F15/INDEX('Taux de change'!$B$5:$B$8,MATCH(D15,'Taux de change'!$A$5:$A$8,0))) | I15: CB en ligne
A16: 17h45–18h15 | B16: Arrivée aéroport El Alto + récupération bagages | I16: —
A17: 18h15–19h30 | B17: Navette / taxi vers centre La Paz (El Alto à 4 100 m, route sinueuse, 30 min) | C17: Minibus partagé (puerta a puerta) Bs 15–25. Taxi seul Bs 40–60. | D17: BOB | E17: 15 | F17: 40 | G17: =IF(D17="","",E17/INDEX('Taux de change'!$B$5:$B$8,MATCH(D17,'Taux de change'!$A$5:$A$8,0))) | H17: =IF(D17="","",F17/INDEX('Taux de change'!$B$5:$B$8,MATCH(D17,'Taux de change'!$A$5:$A$8,0))) | I17: Espèces / CB
A18: 19h30–20h00 | B18: Check-in hostel La Paz — lit en dortoir (privée : Bs 180–280) | D18: BOB | E18: 70 | F18: 125 | G18: =IF(D18="","",E18/INDEX('Taux de change'!$B$5:$B$8,MATCH(D18,'Taux de change'!$A$5:$A$8,0))) | H18: =IF(D18="","",F18/INDEX('Taux de change'!$B$5:$B$8,MATCH(D18,'Taux de change'!$A$5:$A$8,0))) | I18: CB / esp.
A19: 20h00–21h00 | B19: Dîner léger : sopa de quinua | D19: BOB | E19: 25 | F19: 40 | G19: =IF(D19="","",E19/INDEX('Taux de change'!$B$5:$B$8,MATCH(D19,'Taux de change'!$A$5:$A$8,0))) | H19: =IF(D19="","",F19/INDEX('Taux de change'!$B$5:$B$8,MATCH(D19,'Taux de change'!$A$5:$A$8,0))) | I19: Espèces
B20: TOTAL JOUR | G20: =SUM(G6:G19) | H20: =SUM(H6:H19)

Sheet J02 - La Paz J1
A1: JOUR 2 — LA PAZ (Bolivie) — jour 1
A2: Acclimatation et exploration — téléphériques, marchés
A3: Altitude : 3 640 m
A5: Horaires | B5: Activité / prestation | C5: Détail, vigilance, alternative | D5: Devise | E5: Coût local min | F5: Coût local max | G5: Coût USD min | H5: Coût USD max | I5: Paiement
A6: 08h00–08h45 | B6: Petit-déjeuner : api con pastel au Mercado Rodríguez | D6: BOB | E6: 10 | F6: 18 | G6: =IF(D6="","",E6/INDEX('Taux de change'!$B$5:$B$8,MATCH(D6,'Taux de change'!$A$5:$A$8,0))) | H6: =IF(D6="","",F6/INDEX('Taux de change'!$B$5:$B$8,MATCH(D6,'Taux de change'!$A$5:$A$8,0))) | I6: Espèces
A7: 09h00–12h00 | B7: Free walking tour (Red Cap Walking Tours, départ 11h00 Plaza San Pedro) — pourboire attendu | D7: BOB | E7: 50 | F7: 80 | G7: =IF(D7="","",E7/INDEX('Taux de change'!$B$5:$B$8,MATCH(D7,'Taux de change'!$A$5:$A$8,0))) | H7: =IF(D7="","",F7/INDEX('Taux de change'!$B$5:$B$8,MATCH(D7,'Taux de change'!$A$5:$A$8,0))) | I7: Espèces
A8: 12h00–12h15 | B8: Mi Teleférico — ligne Rouge : Estación Central → El Alto (16 de Julio), 4 000 m | D8: BOB | E8: 3 | F8: 3 | G8: =IF(D8="","",E8/INDEX('Taux de change'!$B$5:$B$8,MATCH(D8,'Taux de change'!$A$5:$A$8,0))) | H8: =IF(D8="","",F8/INDEX('Taux de change'!$B$5:$B$8,MATCH(D8,'Taux de change'!$A$5:$A$8,0))) | I8: Espèces / QR
A9: 12h15–13h30 | B9: Mirador d'El Alto sur toute la cuvette + Feria 16 de Julio (jeudi et dimanche, l'un des plus grands marchés) | I9: —
A10: 13h30–14h30 | B10: Almuerzo : trucha frita + mate de coca | D10: BOB | E10: 25 | F10: 40 | G10: =IF(D10="","",E10/INDEX('Taux de change'!$B$5:$B$8,MATCH(D10,'Taux de change'!$A$5:$A$8,0))) | H10: =IF(D10="","",F10/INDEX('Taux de change'!$B$5:$B$8,MATCH(D10,'Taux de change'!$A$5:$A$8,0))) | I10: Espèces
A11: 14h30–16h00 | B11: Cimetière général (arquitectura de las tumbas, peintures sur les façades) — mototaxi aller/retour | D11: BOB | E11: 15 | F11: 25 | G11: =IF(D11="","",E11/INDEX('Taux de change'!$B$5:$B$8,MATCH(D11,'Taux de change'!$A$5:$A$8,0))) | H11: =IF(D11="","",F11/INDEX('Taux de change'!$B$5:$B$8,MATCH(D11,'Taux de change'!$A$5:$A$8,0))) | I11: Espèces
A12: 16h00–17h30 | B12: Mi Teleférico — ligne Jaune : Estación de Artes → Sopocachi (vue de nuit sur la cuvette) | D12: BOB | E12: 3 | F12: 3 | G12: =IF(D12="","",E12/INDEX('Taux de change'!$B$5:$B$8,MATCH(D12,'Taux de change'!$A$5:$A$8,0))) | H12: =IF(D12="","",F12/INDEX('Taux de change'!$B$5:$B$8,MATCH(D12,'Taux de change'!$A$5:$A$8,0))) | I12: Espèces / QR
A13: 18h00–19h00 | B13: Marché artisanal + change complémentaire (Calle Sagárnaga) | D13: BOB | E13: 0 | F13: 60 | G13: =IF(D13="","",E13/INDEX('Taux de change'!$B$5:$B$8,MATCH(D13,'Taux de change'!$A$5:$A$8,0))) | H13: =IF(D13="","",F13/INDEX('Taux de change'!$B$5:$B$8,MATCH(D13,'Taux de change'!$A$5:$A$8,0))) | I13: Espèces
A14: 19h30–20h30 | B14: Dîner à Sopocachi : plat + bière Paceña | D14: BOB | E14: 45 | F14: 70 | G14: =IF(D14="","",E14/INDEX('Taux de change'!$B$5:$B$8,MATCH(D14,'Taux de change'!$A$5:$A$8,0))) | H14: =IF(D14="","",F14/INDEX('Taux de change'!$B$5:$B$8,MATCH(D14,'Taux de change'!$A$5:$A$8,0))) | I14: CB / esp.
A15: — | B15: Retrait au DAB (BCP, Banco Unión) — plafonds Bs 700–2 000 | D15: BOB | E15: 25 | F15: 35 | G15: =IF(D15="","",E15/INDEX('Taux de change'!$B$5:$B$8,MATCH(D15,'Taux de change'!$A$5:$A$8,0))) | H15: =IF(D15="","",F15/INDEX('Taux de change'!$B$5:$B$8,MATCH(D15,'Taux de change'!$A$5:$A$8,0))) | I15: Espèces
B16: TOTAL JOUR | G16: =SUM(G6:G15) | H16: =SUM(H6:H15)

Sheet J03 - La Paz J2
A1: JOUR 3 — LA PAZ (Bolivie) — jour 2
A2: Musées et préparation du vol vers Asunción
A3: Altitude : 3 640 m
A5: Horaires | B5: Activité / prestation | C5: Détail, vigilance, alternative | D5: Devise | E5: Coût local min | F5: Coût local max | G5: Coût USD min | H5: Coût USD max | I5: Paiement
A6: 08h00–09h00 | B6: Petit-déjeuner à l'hostal | D6: BOB | E6: 10 | F6: 15 | G6: =IF(D6="","",E6/INDEX('Taux de change'!$B$5:$B$8,MATCH(D6,'Taux de change'!$A$5:$A$8,0))) | H6: =IF(D6="","",F6/INDEX('Taux de change'!$B$5:$B$8,MATCH(D6,'Taux de change'!$A$5:$A$8,0))) | I6: Espèces
A7: 09h30–11h30 | B7: Musée de l'art précolombien (Tiwanaku, Inca) — Casa del Corregidor | D7: BOB | E7: 25 | F7: 25 | G7: =IF(D7="","",E7/INDEX('Taux de change'!$B$5:$B$8,MATCH(D7,'Taux de change'!$A$5:$A$8,0))) | H7: =IF(D7="","",F7/INDEX('Taux de change'!$B$5:$B$8,MATCH(D7,'Taux de change'!$A$5:$A$8,0))) | I7: Espèces / CB
A8: 12h00–13h00 | B8: Almuerzo : lomo saltado + jugo de naranja | D8: BOB | E8: 30 | F8: 45 | G8: =IF(D8="","",E8/INDEX('Taux de change'!$B$5:$B$8,MATCH(D8,'Taux de change'!$A$5:$A$8,0))) | H8: =IF(D8="","",F8/INDEX('Taux de change'!$B$5:$B$8,MATCH(D8,'Taux de change'!$A$5:$A$8,0))) | I8: Espèces / CB
A9: 14h00–15h30 | B9: Libre : Église San Francisco, Plaza Murillo, Palais du gouvernement (extérieur) | D9: BOB | E9: 0 | F9: 30 | G9: =IF(D9="","",E9/INDEX('Taux de change'!$B$5:$B$8,MATCH(D9,'Taux de change'!$A$5:$A$8,0))) | H9: =IF(D9="","",F9/INDEX('Taux de change'!$B$5:$B$8,MATCH(D9,'Taux de change'!$A$5:$A$8,0))) | I9: —
A10: 15h30–16h30 | B10: Retrait DAB complémentaire + change Bs → PYG auprès casa de cambio (taux 5–7 % moins bon qu'à Asunción) | C10: Ne changez ici que PYG 500 000–800 000 ; le reste à Asunción. | D10: BOB | E10: 25 | F10: 50 | G10: =IF(D10="","",E10/INDEX('Taux de change'!$B$5:$B$8,MATCH(D10,'Taux de change'!$A$5:$A$8,0))) | H10: =IF(D10="","",F10/INDEX('Taux de change'!$B$5:$B$8,MATCH(D10,'Taux de change'!$A$5:$A$8,0))) | I10: Espèces
A11: 16h30–17h30 | B11: Transfert taxi vers aéroport El Alto (El Alto à 4 150 m) | C11: Compter 45 min–1 h selon le trafic et la météo. | D11: BOB | E11: 20 | F11: 40 | G11: =IF(D11="","",E11/INDEX('Taux de change'!$B$5:$B$8,MATCH(D11,'Taux de change'!$A$5:$A$8,0))) | H11: =IF(D11="","",F11/INDEX('Taux de change'!$B$5:$B$8,MATCH(D11,'Taux de change'!$A$5:$A$8,0))) | I11: Espèces / CB
A12: 17h30–18h30 | B12: Enregistrement + tasa de embarque + passage sécurité | D12: BOB | E12: 8 | F12: 8 | G12: =IF(D12="","",E12/INDEX('Taux de change'!$B$5:$B$8,MATCH(D12,'Taux de change'!$A$5:$A$8,0))) | H12: =IF(D12="","",F12/INDEX('Taux de change'!$B$5:$B$8,MATCH(D12,'Taux de change'!$A$5:$A$8,0))) | I12: Espèces
A13: 18h30–19h00 | B13: Repas / boissons en zone d'embarquement | D13: BOB | E13: 20 | F13: 35 | G13: =IF(D13="","",E13/INDEX('Taux de change'!$B$5:$B$8,MATCH(D13,'Taux de change'!$A$5:$A$8,0))) | H13: =IF(D13="","",F13/INDEX('Taux de change'!$B$5:$B$8,MATCH(D13,'Taux de change'!$A$5:$A$8,0))) | I13: Espèces
A14: 19h00 | B14: VOL LA PAZ → ASUNCIÓN — Latam, Viva Air · vol direct · 2 h 15 min · boisson incluse | C14: Réserver sur kayak.com.bo ou latam.com. Départ 19h00, arrivée 21h15 (−1 h Paraguay). | D14: BOB | E14: 200 | F14: 400 | G14: =IF(D14="","",E14/INDEX('Taux de change'!$B$5:$B$8,MATCH(D14,'Taux de change'!$A$5:$A$8,0))) | H14: =IF(D14="","",F14/INDEX('Taux de change'!$B$5:$B$8,MATCH(D14,'Taux de change'!$A$5:$A$8,0))) | I14: CB en ligne
A15: 21h15–21h45 | B15: Arrivée aéroport Silvio Pettirossi (CMS) + récupération bagages | I15: —
A16: 22h00–23h00 | B16: Taxi / minibus vers centre Asunción (15 km) | C16: Taxi blanc environ 150 000–200 000 Gs. Minibus partagé plus abordable. | D16: PYG | E16: 50000 | F16: 90000 | G16: =IF(D16="","",E16/INDEX('Taux de change'!$B$5:$B$8,MATCH(D16,'Taux de change'!$A$5:$A$8,0))) | H16: =IF(D16="","",F16/INDEX('Taux de change'!$B$5:$B$8,MATCH(D16,'Taux de change'!$A$5:$A$8,0))) | I16: Espèces / CB
A17: 23h00–23h30 | B17: Check-in hostel Asunción — lit en dortoir | D17: PYG | E17: 80000 | F17: 150000 | G17: =IF(D17="","",E17/INDEX('Taux de change'!$B$5:$B$8,MATCH(D17,'Taux de change'!$A$5:$A$8,0))) | H17: =IF(D17="","",F17/INDEX('Taux de change'!$B$5:$B$8,MATCH(D17,'Taux de change'!$A$5:$A$8,0))) | I17: CB / esp.
B18: TOTAL JOUR | G18: =SUM(G6:G17) | H18: =SUM(H6:H17)

Sheet J04 - Asunción J1
A1: JOUR 4 — ASUNCIÓN (Paraguay) — jour 1
A2: Acclimatation et exploration du centre historique
A3: Altitude : 54 m
A5: Horaires | B5: Activité / prestation | C5: Détail, vigilance, alternative | D5: Devise | E5: Coût local min | F5: Coût local max | G5: Coût USD min | H5: Coût USD max | I5: Paiement
A6: 08h30–09h30 | B6: Petit-déjeuner : café + medialunas + tereré (boisson typique) | D6: PYG | E6: 8000 | F6: 15000 | G6: =IF(D6="","",E6/INDEX('Taux de change'!$B$5:$B$8,MATCH(D6,'Taux de change'!$A$5:$A$8,0))) | H6: =IF(D6="","",F6/INDEX('Taux de change'!$B$5:$B$8,MATCH(D6,'Taux de change'!$A$5:$A$8,0))) | I6: Espèces
A7: 10h00–12h00 | B7: Free walking tour Asunción (départ Plaza de Armas) — pourboire attendu | D7: PYG | E7: 50000 | F7: 80000 | G7: =IF(D7="","",E7/INDEX('Taux de change'!$B$5:$B$8,MATCH(D7,'Taux de change'!$A$5:$A$8,0))) | H7: =IF(D7="","",F7/INDEX('Taux de change'!$B$5:$B$8,MATCH(D7,'Taux de change'!$A$5:$A$8,0))) | I7: Espèces
A8: 12h15–12h45 | B8: Métro Asunción (unique ligne, courte mais emblématique) aller-retour pour voir Luque | C8: Billet unique à l'avance, sinon vente à l'unité. | D8: PYG | E8: 3500 | F8: 3500 | G8: =IF(D8="","",E8/INDEX('Taux de change'!$B$5:$B$8,MATCH(D8,'Taux de change'!$A$5:$A$8,0))) | H8: =IF(D8="","",F8/INDEX('Taux de change'!$B$5:$B$8,MATCH(D8,'Taux de change'!$A$5:$A$8,0))) | I8: Espèces / CB
A9: 13h00–14h00 | B9: Almuerzo : sopa paraguaya + ensalada de tomate + jus de papaye | D9: PYG | E9: 20000 | F9: 35000 | G9: =IF(D9="","",E9/INDEX('Taux de change'!$B$5:$B$8,MATCH(D9,'Taux de change'!$A$5:$A$8,0))) | H9: =IF(D9="","",F9/INDEX('Taux de change'!$B$5:$B$8,MATCH(D9,'Taux de change'!$A$5:$A$8,0))) | I9: Espèces
A10: 14h30–16h00 | B10: Musée du Palais López (extérieur), Cathédrale métropolitaine (visite libre), Cabildo colonial | D10: PYG | E10: 0 | F10: 20000 | G10: =IF(D10="","",E10/INDEX('Taux de change'!$B$5:$B$8,MATCH(D10,'Taux de change'!$A$5:$A$8,0))) | H10: =IF(D10="","",F10/INDEX('Taux de change'!$B$5:$B$8,MATCH(D10,'Taux de change'!$A$5:$A$8,0))) | I10: Espèces / CB
A11: 16h00–17h30 | B11: Marché Pettirossi (artisanat, bordados) — mototaxi aller/retour | D11: PYG | E11: 15000 | F11: 25000 | G11: =IF(D11="","",E11/INDEX('Taux de change'!$B$5:$B$8,MATCH(D11,'Taux de change'!$A$5:$A$8,0))) | H11: =IF(D11="","",F11/INDEX('Taux de change'!$B$5:$B$8,MATCH(D11,'Taux de change'!$A$5:$A$8,0))) | I11: Espèces
A12: 18h00–19h00 | B12: Change PYG (si besoin) + retrait DAB (BCP, Itaú, Banco del Barrio) | C12: Plafonds 500 000–1 500 000 Gs par retrait. Taux moins bon qu'en Pérou. | D12: PYG | E12: 25000 | F12: 40000 | G12: =IF(D12="","",E12/INDEX('Taux de change'!$B$5:$B$8,MATCH(D12,'Taux de change'!$A$5:$A$8,0))) | H12: =IF(D12="","",F12/INDEX('Taux de change'!$B$5:$B$8,MATCH(D12,'Taux de change'!$A$5:$A$8,0))) | I12: Espèces
A13: 19h30–20h30 | B13: Dîner : chop suey asunceño (pâtes + viande) + cerveza Brahma | D13: PYG | E13: 30000 | F13: 50000 | G13: =IF(D13="","",E13/INDEX('Taux de change'!$B$5:$B$8,MATCH(D13,'Taux de change'!$A$5:$A$8,0))) | H13: =IF(D13="","",F13/INDEX('Taux de change'!$B$5:$B$8,MATCH(D13,'Taux de change'!$A$5:$A$8,0))) | I13: CB / esp.
A14: — | B14: Eau 4 L + snacks pour les trajets | D14: PYG | E14: 5000 | F14: 10000 | G14: =IF(D14="","",E14/INDEX('Taux de change'!$B$5:$B$8,MATCH(D14,'Taux de change'!$A$5:$A$8,0))) | H14: =IF(D14="","",F14/INDEX('Taux de change'!$B$5:$B$8,MATCH(D14,'Taux de change'!$A$5:$A$8,0))) | I14: Espèces
B15: TOTAL JOUR | G15: =SUM(G6:G14) | H15: =SUM(H6:H14)

Sheet J05 - Asunción J2
A1: JOUR 5 — ASUNCIÓN (Paraguay) — jour 2
A2: Riviera Paraguay et préparation du vol vers Rio
A3: Altitude : 54 m
A5: Horaires | B5: Activité / prestation | C5: Détail, vigilance, alternative | D5: Devise | E5: Coût local min | F5: Coût local max | G5: Coût USD min | H5: Coût USD max | I5: Paiement
A6: 08h30–09h30 | B6: Petit-déjeuner à l'hostal | D6: PYG | E6: 8000 | F6: 12000 | G6: =IF(D6="","",E6/INDEX('Taux de change'!$B$5:$B$8,MATCH(D6,'Taux de change'!$A$5:$A$8,0))) | H6: =IF(D6="","",F6/INDEX('Taux de change'!$B$5:$B$8,MATCH(D6,'Taux de change'!$A$5:$A$8,0))) | I6: Espèces
A7: 10h00–13h00 | B7: Paseo Costanero (rivière Paraguay) — balade sans guide, photos, parc de la Riviera | D7: PYG | E7: 0 | F7: 15000 | G7: =IF(D7="","",E7/INDEX('Taux de change'!$B$5:$B$8,MATCH(D7,'Taux de change'!$A$5:$A$8,0))) | H7: =IF(D7="","",F7/INDEX('Taux de change'!$B$5:$B$8,MATCH(D7,'Taux de change'!$A$5:$A$8,0))) | I7: Espèces
A8: 13h00–14h00 | B8: Almuerzo : milanesas + ensalada + jugo | D8: PYG | E8: 20000 | F8: 35000 | G8: =IF(D8="","",E8/INDEX('Taux de change'!$B$5:$B$8,MATCH(D8,'Taux de change'!$A$5:$A$8,0))) | H8: =IF(D8="","",F8/INDEX('Taux de change'!$B$5:$B$8,MATCH(D8,'Taux de change'!$A$5:$A$8,0))) | I8: Espèces
A9: 14h30–16h00 | B9: Marché flottant (domingo a jueves) ou Feria Americana si fermé | C9: Feria Americana : fripes, électronique, fourre-tout. | D9: PYG | E9: 0 | F9: 50000 | G9: =IF(D9="","",E9/INDEX('Taux de change'!$B$5:$B$8,MATCH(D9,'Taux de change'!$A$5:$A$8,0))) | H9: =IF(D9="","",F9/INDEX('Taux de change'!$B$5:$B$8,MATCH(D9,'Taux de change'!$A$5:$A$8,0))) | I9: Espèces
A10: 16h00–17h00 | B10: Retrait DAB final + change restant PYG → BRL (taux 10–12 % moins bon qu'au Brésil) | D10: PYG | E10: 25000 | F10: 50000 | G10: =IF(D10="","",E10/INDEX('Taux de change'!$B$5:$B$8,MATCH(D10,'Taux de change'!$A$5:$A$8,0))) | H10: =IF(D10="","",F10/INDEX('Taux de change'!$B$5:$B$8,MATCH(D10,'Taux de change'!$A$5:$A$8,0))) | I10: Espèces
A11: 17h00–18h00 | B11: Transfert taxi vers aéroport Silvio Pettirossi | C11: 15 km, 20–30 min selon trafic. | D11: PYG | E11: 50000 | F11: 100000 | G11: =IF(D11="","",E11/INDEX('Taux de change'!$B$5:$B$8,MATCH(D11,'Taux de change'!$A$5:$A$8,0))) | H11: =IF(D11="","",F11/INDEX('Taux de change'!$B$5:$B$8,MATCH(D11,'Taux de change'!$A$5:$A$8,0))) | I11: Espèces / CB
A12: 18h00–19h00 | B12: Enregistrement + tasa de embarque + sécurité | D12: PYG | E12: 10000 | F12: 10000 | G12: =IF(D12="","",E12/INDEX('Taux de change'!$B$5:$B$8,MATCH(D12,'Taux de change'!$A$5:$A$8,0))) | H12: =IF(D12="","",F12/INDEX('Taux de change'!$B$5:$B$8,MATCH(D12,'Taux de change'!$A$5:$A$8,0))) | I12: Espèces
A13: 19h00–19h30 | B13: Repas / boissons en zone d'embarquement | D13: PYG | E13: 20000 | F13: 40000 | G13: =IF(D13="","",E13/INDEX('Taux de change'!$B$5:$B$8,MATCH(D13,'Taux de change'!$A$5:$A$8,0))) | H13: =IF(D13="","",F13/INDEX('Taux de change'!$B$5:$B$8,MATCH(D13,'Taux de change'!$A$5:$A$8,0))) | I13: Espèces
A14: 19h30 | B14: VOL ASUNCIÓN → RIO DE JANEIRO — Latam, Azul, Gol · vol direct · 2 h 45 min · boisson + snack | C14: Réserver sur decolar.com.py, latam.com ou directement cie aérienne. Départ 19h30, arrivée 21h15 (+1 h Brésil). | D14: PYG | E14: 300000 | F14: 550000 | G14: =IF(D14="","",E14/INDEX('Taux de change'!$B$5:$B$8,MATCH(D14,'Taux de change'!$A$5:$A$8,0))) | H14: =IF(D14="","",F14/INDEX('Taux de change'!$B$5:$B$8,MATCH(D14,'Taux de change'!$A$5:$A$8,0))) | I14: CB en ligne
A15: 21h15–21h45 | B15: Arrivée aéroport Santos Dumont (SDU) ou Galeão (GIG) + récupération bagages | I15: —
A16: 22h00–23h30 | B16: Transfert taxi / Uber vers centre Rio / Copacabana (45–70 km selon aéroport) | C16: Uber depuis le téléphone = meilleur prix. Santos Dumont plus proche du centre. | D16: BRL | E16: 60 | F16: 120 | G16: =IF(D16="","",E16/INDEX('Taux de change'!$B$5:$B$8,MATCH(D16,'Taux de change'!$A$5:$A$8,0))) | H16: =IF(D16="","",F16/INDEX('Taux de change'!$B$5:$B$8,MATCH(D16,'Taux de change'!$A$5:$A$8,0))) | I16: CB (in-app)
A17: 23h30–00h00 | B17: Check-in hostel Rio — lit en dortoir (Lapa ou Copacabana) | D17: BRL | E17: 80 | F17: 150 | G17: =IF(D17="","",E17/INDEX('Taux de change'!$B$5:$B$8,MATCH(D17,'Taux de change'!$A$5:$A$8,0))) | H17: =IF(D17="","",F17/INDEX('Taux de change'!$B$5:$B$8,MATCH(D17,'Taux de change'!$A$5:$A$8,0))) | I17: CB / esp.
B18: TOTAL JOUR | G18: =SUM(G6:G17) | H18: =SUM(H6:H17)

Sheet J06 - Rio J1
A1: JOUR 6 — RIO DE JANEIRO (Brésil) — jour 1
A2: Acclimatation et plages — Copacabana et Ipanema
A3: Altitude : 6 m
A5: Horaires | B5: Activité / prestation | C5: Détail, vigilance, alternative | D5: Devise | E5: Coût local min | F5: Coût local max | G5: Coût USD min | H5: Coût USD max | I5: Paiement
A6: 09h00–10h00 | B6: Petit-déjeuner : café + pão de queijo + suco de laranja (jus d'orange frais) | D6: BRL | E6: 12 | F6: 20 | G6: =IF(D6="","",E6/INDEX('Taux de change'!$B$5:$B$8,MATCH(D6,'Taux de change'!$A$5:$A$8,0))) | H6: =IF(D6="","",F6/INDEX('Taux de change'!$B$5:$B$8,MATCH(D6,'Taux de change'!$A$5:$A$8,0))) | I6: Espèces
A7: 10h30–12h00 | B7: Plage Copacabana — bain, repos après 3 vols | C7: Louer une chaise + parasol Bs 20–30. Agua de coco fresco : R$ 8–12. | D7: BRL | E7: 0 | F7: 50 | G7: =IF(D7="","",E7/INDEX('Taux de change'!$B$5:$B$8,MATCH(D7,'Taux de change'!$A$5:$A$8,0))) | H7: =IF(D7="","",F7/INDEX('Taux de change'!$B$5:$B$8,MATCH(D7,'Taux de change'!$A$5:$A$8,0))) | I7: Espèces / CB
A8: 12h30–13h30 | B8: Almuerzo : peixe grelhado à Moqueca (ragoût de poisson) + agua com gás (eau gazeuse) | D8: BRL | E8: 30 | F8: 50 | G8: =IF(D8="","",E8/INDEX('Taux de change'!$B$5:$B$8,MATCH(D8,'Taux de change'!$A$5:$A$8,0))) | H8: =IF(D8="","",F8/INDEX('Taux de change'!$B$5:$B$8,MATCH(D8,'Taux de change'!$A$5:$A$8,0))) | I8: Espèces / CB
A9: 14h00–16h00 | B9: Promenade Copacabana → Arpoador (pic rocheux) → Ipanema, arrêts photos | D9: BRL | E9: 0 | F9: 20 | G9: =IF(D9="","",E9/INDEX('Taux de change'!$B$5:$B$8,MATCH(D9,'Taux de change'!$A$5:$A$8,0))) | H9: =IF(D9="","",F9/INDEX('Taux de change'!$B$5:$B$8,MATCH(D9,'Taux de change'!$A$5:$A$8,0))) | I9: —
A10: 16h30–17h30 | B10: Marché artisanal Ipanema (Praça General Osório dimanche) ou boutiques Rua Garcia d'Ávila | D10: BRL | E10: 0 | F10: 100 | G10: =IF(D10="","",E10/INDEX('Taux de change'!$B$5:$B$8,MATCH(D10,'Taux de change'!$A$5:$A$8,0))) | H10: =IF(D10="","",F10/INDEX('Taux de change'!$B$5:$B$8,MATCH(D10,'Taux de change'!$A$5:$A$8,0))) | I10: CB / esp.
A11: 18h00–19h00 | B11: Retrait DAB final (Bradesco, Itaú) + change si besoin | C11: Plafonds R$ 500–1 000 par retrait, DAB souvent pleins. | D11: BRL | E11: 20 | F11: 40 | G11: =IF(D11="","",E11/INDEX('Taux de change'!$B$5:$B$8,MATCH(D11,'Taux de change'!$A$5:$A$8,0))) | H11: =IF(D11="","",F11/INDEX('Taux de change'!$B$5:$B$8,MATCH(D11,'Taux de change'!$A$5:$A$8,0))) | I11: Espèces
A12: 19h30–20h30 | B12: Dîner : churrasco (brochettes grillées) + bière Brahma | D12: BRL | E12: 50 | F12: 80 | G12: =IF(D12="","",E12/INDEX('Taux de change'!$B$5:$B$8,MATCH(D12,'Taux de change'!$A$5:$A$8,0))) | H12: =IF(D12="","",F12/INDEX('Taux de change'!$B$5:$B$8,MATCH(D12,'Taux de change'!$A$5:$A$8,0))) | I12: CB / esp.
A13: — | B13: Eau 2 L + fruits (banane, orange) — marché local moins cher | D13: BRL | E13: 10 | F13: 15 | G13: =IF(D13="","",E13/INDEX('Taux de change'!$B$5:$B$8,MATCH(D13,'Taux de change'!$A$5:$A$8,0))) | H13: =IF(D13="","",F13/INDEX('Taux de change'!$B$5:$B$8,MATCH(D13,'Taux de change'!$A$5:$A$8,0))) | I13: Espèces
B14: TOTAL JOUR | G14: =SUM(G6:G13) | H14: =SUM(H6:H13)

Sheet J07 - Rio J2
A1: JOUR 7 — RIO DE JANEIRO (Brésil) — jour 2
A2: Christ Rédempteur et montagne du Pain de Sucre
A3: Altitude : 6 m
A5: Horaires | B5: Activité / prestation | C5: Détail, vigilance, alternative | D5: Devise | E5: Coût local min | F5: Coût local max | G5: Coût USD min | H5: Coût USD max | I5: Paiement
A6: 08h00–09h00 | B6: Petit-déjeuner à l'hostal | D6: BRL | E6: 10 | F6: 15 | G6: =IF(D6="","",E6/INDEX('Taux de change'!$B$5:$B$8,MATCH(D6,'Taux de change'!$A$5:$A$8,0))) | H6: =IF(D6="","",F6/INDEX('Taux de change'!$B$5:$B$8,MATCH(D6,'Taux de change'!$A$5:$A$8,0))) | I6: Espèces
A7: 09h30–10h30 | B7: Train à crémaillère + entrée Christ Rédempteur (Corcovado, 709 m) | C7: Accès par: train dentelle départ Cosme Velho (45 min aller) ou van (15 min). Pluie fréquente = photos floues. | D7: BRL | E7: 95 | F7: 130 | G7: =IF(D7="","",E7/INDEX('Taux de change'!$B$5:$B$8,MATCH(D7,'Taux de change'!$A$5:$A$8,0))) | H7: =IF(D7="","",F7/INDEX('Taux de change'!$B$5:$B$8,MATCH(D7,'Taux de change'!$A$5:$A$8,0))) | I7: CB en ligne
A8: 10h30–12h00 | B8: Visite statue du Christ (7,5 t, 40 m, vue à 360° sur la baie de Guanabara) | I8: —
A9: 12h00–13h30 | B9: Descente + déjeuner léger en chemin | D9: BRL | E9: 20 | F9: 40 | G9: =IF(D9="","",E9/INDEX('Taux de change'!$B$5:$B$8,MATCH(D9,'Taux de change'!$A$5:$A$8,0))) | H9: =IF(D9="","",F9/INDEX('Taux de change'!$B$5:$B$8,MATCH(D9,'Taux de change'!$A$5:$A$8,0))) | I9: Espèces
A10: 14h00–15h00 | B10: Ascenseur incliné vers Pain de Sucre (Pão de Açúcar, 396 m) | C10: 2 téléphériques successifs. Vue spectaculaire sur Copacabana et Baie. | D10: BRL | E10: 70 | F10: 100 | G10: =IF(D10="","",E10/INDEX('Taux de change'!$B$5:$B$8,MATCH(D10,'Taux de change'!$A$5:$A$8,0))) | H10: =IF(D10="","",F10/INDEX('Taux de change'!$B$5:$B$8,MATCH(D10,'Taux de change'!$A$5:$A$8,0))) | I10: CB en ligne
A11: 15h00–17h00 | B11: Panoramas, photos au coucher du soleil | C11: Bar/café au sommet (chers). Redescendre avant 18h (fermeture). | D11: BRL | E11: 0 | F11: 50 | G11: =IF(D11="","",E11/INDEX('Taux de change'!$B$5:$B$8,MATCH(D11,'Taux de change'!$A$5:$A$8,0))) | H11: =IF(D11="","",F11/INDEX('Taux de change'!$B$5:$B$8,MATCH(D11,'Taux de change'!$A$5:$A$8,0))) | I11: Espèces / CB
A12: 17h30–18h30 | B12: Marche Ipanema ou Barra da Tijuca selon l'envie | D12: BRL | E12: 0 | F12: 30 | G12: =IF(D12="","",E12/INDEX('Taux de change'!$B$5:$B$8,MATCH(D12,'Taux de change'!$A$5:$A$8,0))) | H12: =IF(D12="","",F12/INDEX('Taux de change'!$B$5:$B$8,MATCH(D12,'Taux de change'!$A$5:$A$8,0))) | I12: Espèces
A13: 19h00–20h00 | B13: Dîner : feijoada (ragoût d'haricots noirs + porc) — restaurant local (pas touristique) | D13: BRL | E13: 40 | F13: 70 | G13: =IF(D13="","",E13/INDEX('Taux de change'!$B$5:$B$8,MATCH(D13,'Taux de change'!$A$5:$A$8,0))) | H13: =IF(D13="","",F13/INDEX('Taux de change'!$B$5:$B$8,MATCH(D13,'Taux de change'!$A$5:$A$8,0))) | I13: CB / esp.
B14: TOTAL JOUR | G14: =SUM(G6:G13) | H14: =SUM(H6:H13)

Sheet J08 - Rio J3
A1: JOUR 8 — RIO DE JANEIRO (Brésil) — jour 3
A2: Derniers sites, shopping et départ
A3: Altitude : 6 m
A5: Horaires | B5: Activité / prestation | C5: Détail, vigilance, alternative | D5: Devise | E5: Coût local min | F5: Coût local max | G5: Coût USD min | H5: Coût USD max | I5: Paiement
A6: 09h00–10h00 | B6: Petit-déjeuner | D6: BRL | E6: 10 | F6: 20 | G6: =IF(D6="","",E6/INDEX('Taux de change'!$B$5:$B$8,MATCH(D6,'Taux de change'!$A$5:$A$8,0))) | H6: =IF(D6="","",F6/INDEX('Taux de change'!$B$5:$B$8,MATCH(D6,'Taux de change'!$A$5:$A$8,0))) | I6: Espèces
A7: 10h30–12h00 | B7: Jardin botanique (orchidées, fougères géantes, calme) | D7: BRL | E7: 25 | F7: 35 | G7: =IF(D7="","",E7/INDEX('Taux de change'!$B$5:$B$8,MATCH(D7,'Taux de change'!$A$5:$A$8,0))) | H7: =IF(D7="","",F7/INDEX('Taux de change'!$B$5:$B$8,MATCH(D7,'Taux de change'!$A$5:$A$8,0))) | I7: Espèces / CB
A8: 12h30–14h00 | B8: Almuerzo : ceviche (influence péruvienne) + agua natural | D8: BRL | E8: 35 | F8: 60 | G8: =IF(D8="","",E8/INDEX('Taux de change'!$B$5:$B$8,MATCH(D8,'Taux de change'!$A$5:$A$8,0))) | H8: =IF(D8="","",F8/INDEX('Taux de change'!$B$5:$B$8,MATCH(D8,'Taux de change'!$A$5:$A$8,0))) | I8: Espèces / CB
A9: 14h30–16h30 | B9: Marché d'artisanat final, souvenirs, cadeaux (Saara pour les vraies affaires) | D9: BRL | E9: 0 | F9: 150 | G9: =IF(D9="","",E9/INDEX('Taux de change'!$B$5:$B$8,MATCH(D9,'Taux de change'!$A$5:$A$8,0))) | H9: =IF(D9="","",F9/INDEX('Taux de change'!$B$5:$B$8,MATCH(D9,'Taux de change'!$A$5:$A$8,0))) | I9: CB / esp.
A10: 17h00–18h00 | B10: Transfert vers aéroport (45–60 km selon terminal) + enregistrement | C10: Partir 3–4 h avant le vol. | D10: BRL | E10: 50 | F10: 100 | G10: =IF(D10="","",E10/INDEX('Taux de change'!$B$5:$B$8,MATCH(D10,'Taux de change'!$A$5:$A$8,0))) | H10: =IF(D10="","",F10/INDEX('Taux de change'!$B$5:$B$8,MATCH(D10,'Taux de change'!$A$5:$A$8,0))) | I10: CB (Uber)
A11: 18h00–19h00 | B11: Tasa de embarque + passage sécurité + zone d'embarquement | D11: BRL | E11: 30 | F11: 30 | G11: =IF(D11="","",E11/INDEX('Taux de change'!$B$5:$B$8,MATCH(D11,'Taux de change'!$A$5:$A$8,0))) | H11: =IF(D11="","",F11/INDEX('Taux de change'!$B$5:$B$8,MATCH(D11,'Taux de change'!$A$5:$A$8,0))) | I11: Espèces
A12: 19h00–19h30 | B12: Repas final + derniers achats en zone d'embarquement | D12: BRL | E12: 30 | F12: 60 | G12: =IF(D12="","",E12/INDEX('Taux de change'!$B$5:$B$8,MATCH(D12,'Taux de change'!$A$5:$A$8,0))) | H12: =IF(D12="","",F12/INDEX('Taux de change'!$B$5:$B$8,MATCH(D12,'Taux de change'!$A$5:$A$8,0))) | I12: Espèces
B13: TOTAL JOUR | G13: =SUM(G6:G12) | H13: =SUM(H6:H12)
